Workbook
Name Lista_Etapas: Etapas!$B$2:$B$1000
Name Lista_Subetapas: Subetapas!$B$2:$B$1000
Name Lista_Financeiro_Descricoes: Financeiro!$D$2:$D$31

Sheet Início
A1: Dados da Obra
A2: Nome da Obra
A3: Cliente/Contratante
A4: Endereço
A5: Responsável Técnico
A6: Data Inicial Planejada
A7: Data Final Planejada
A8: Orçamento Inicial (Previsto) | B8: =SUM(Etapas!$F$2:$F$31)

Sheet Etapas
A1: ID (técnico) | B1: Nome | C1: Ordem | D1: Status | E1: ID_Obra (técnico) | F1: Total Previsto (Subetapas)
A2: =IF($B2="","","ETA-"&TEXT(ROW()-1,"0000")) | E2: =IF($B2="","",Base_Dados!$B$2) | F2: =IF($B2="","",SUMIFS(Subetapas!$F:$F,Subetapas!$E:$E,$A2))
A3: =IF($B3="","","ETA-"&TEXT(ROW()-1,"0000")) | E3: =IF($B3="","",Base_Dados!$B$2) | F3: =IF($B3="","",SUMIFS(Subetapas!$F:$F,Subetapas!$E:$E,$A3))
A4: =IF($B4="","","ETA-"&TEXT(ROW()-1,"0000")) | E4: =IF($B4="","",Base_Dados!$B$2) | F4: =IF($B4="","",SUMIFS(Subetapas!$F:$F,Subetapas!$E:$E,$A4))
A5: =IF($B5="","","ETA-"&TEXT(ROW()-1,"0000")) | E5: =IF($B5="","",Base_Dados!$B$2) | F5: =IF($B5="","",SUMIFS(Subetapas!$F:$F,Subetapas!$E:$E,$A5))
A6: =IF($B6="","","ETA-"&TEXT(ROW()-1,"0000")) | E6: =IF($B6="","",Base_Dados!$B$2) | F6: =IF($B6="","",SUMIFS(Subetapas!$F:$F,Subetapas!$E:$E,$A6))
A7: =IF($B7="","","ETA-"&TEXT(ROW()-1,"0000")) | E7: =IF($B7="","",Base_Dados!$B$2) | F7: =IF($B7="","",SUMIFS(Subetapas!$F:$F,Subetapas!$E:$E,$A7))
A8: =IF($B8="","","ETA-"&TEXT(ROW()-1,"0000")) | E8: =IF($B8="","",Base_Dados!$B$2) | F8: =IF($B8="","",SUMIFS(Subetapas!$F:$F,Subetapas!$E:$E,$A8))
A9: =IF($B9="","","ETA-"&TEXT(ROW()-1,"0000")) | E9: =IF($B9="","",Base_Dados!$B$2) | F9: =IF($B9="","",SUMIFS(Subetapas!$F:$F,Subetapas!$E:$E,$A9))
A10: =IF($B10="","","ETA-"&TEXT(ROW()-1,"0000")) | E10: =IF($B10="","",Base_Dados!$B$2) | F10: =IF($B10="","",SUMIFS(Subetapas!$F:$F,Subetapas!$E:$E,$A10))
A11: =IF($B11="","","ETA-"&TEXT(ROW()-1,"0000")) | E11: =IF($B11="","",Base_Dados!$B$2) | F11: =IF($B11="","",SUMIFS(Subetapas!$F:$F,Subetapas!$E:$E,$A11))
A12: =IF($B12="","","ETA-"&TEXT(ROW()-1,"0000")) | E12: =IF($B12="","",Base_Dados!$B$2) | F12: =IF($B12="","",SUMIFS(Subetapas!$F:$F,Subetapas!$E:$E,$A12))
A13: =IF($B13="","","ETA-"&TEXT(ROW()-1,"0000")) | E13: =IF($B13="","",Base_Dados!$B$2) | F13: =IF($B13="","",SUMIFS(Subetapas!$F:$F,Subetapas!$E:$E,$A13))
... A31: =IF($B31="","","ETA-"&TEXT(ROW()-1,"0000")) | E31: =IF($B31="","",Base_Dados!$B$2) | F31: =IF($B31="","",SUMIFS(Subetapas!$F:$F,Subetapas!$E:$E,$A31))

Sheet Subetapas
A1: ID (técnico) | B1: Nome | C1: Etapa | D1: Status | E1: ID_Etapa (técnico) | F1: Total Previsto (Serviços)
A2: =IF($B2="","","SUB-"&TEXT(ROW()-1,"0000")) | E2: =IF($C2="","",INDEX(Etapas!$A:$A,MATCH($C2,Etapas!$B:$B,0))) | F2: =IF($B2="","",SUMIFS(Serviços!$J:$J,Serviços!$M:$M,$A2,Serviços!$L:$L,"<>Cancelado",Serviços!$L:$L,"<>Retirado do Escopo",Serviços!$L:$L,"<>Substituído"))
A3: =IF($B3="","","SUB-"&TEXT(ROW()-1,"0000")) | E3: =IF($C3="","",INDEX(Etapas!$A:$A,MATCH($C3,Etapas!$B:$B,0))) | F3: =IF($B3="","",SUMIFS(Serviços!$J:$J,Serviços!$M:$M,$A3,Serviços!$L:$L,"<>Cancelado",Serviços!$L:$L,"<>Retirado do Escopo",Serviços!$L:$L,"<>Substituído"))
A4: =IF($B4="","","SUB-"&TEXT(ROW()-1,"0000")) | E4: =IF($C4="","",INDEX(Etapas!$A:$A,MATCH($C4,Etapas!$B:$B,0))) | F4: =IF($B4="","",SUMIFS(Serviços!$J:$J,Serviços!$M:$M,$A4,Serviços!$L:$L,"<>Cancelado",Serviços!$L:$L,"<>Retirado do Escopo",Serviços!$L:$L,"<>Substituído"))
A5: =IF($B5="","","SUB-"&TEXT(ROW()-1,"0000")) | E5: =IF($C5="","",INDEX(Etapas!$A:$A,MATCH($C5,Etapas!$B:$B,0))) | F5: =IF($B5="","",SUMIFS(Serviços!$J:$J,Serviços!$M:$M,$A5,Serviços!$L:$L,"<>Cancelado",Serviços!$L:$L,"<>Retirado do Escopo",Serviços!$L:$L,"<>Substituído"))
A6: =IF($B6="","","SUB-"&TEXT(ROW()-1,"0000")) | E6: =IF($C6="","",INDEX(Etapas!$A:$A,MATCH($C6,Etapas!$B:$B,0))) | F6: =IF($B6="","",SUMIFS(Serviços!$J:$J,Serviços!$M:$M,$A6,Serviços!$L:$L,"<>Cancelado",Serviços!$L:$L,"<>Retirado do Escopo",Serviços!$L:$L,"<>Substituído"))
A7: =IF($B7="","","SUB-"&TEXT(ROW()-1,"0000")) | E7: =IF($C7="","",INDEX(Etapas!$A:$A,MATCH($C7,Etapas!$B:$B,0))) | F7: =IF($B7="","",SUMIFS(Serviços!$J:$J,Serviços!$M:$M,$A7,Serviços!$L:$L,"<>Cancelado",Serviços!$L:$L,"<>Retirado do Escopo",Serviços!$L:$L,"<>Substituído"))
A8: =IF($B8="","","SUB-"&TEXT(ROW()-1,"0000")) | E8: =IF($C8="","",INDEX(Etapas!$A:$A,MATCH($C8,Etapas!$B:$B,0))) | F8: =IF($B8="","",SUMIFS(Serviços!$J:$J,Serviços!$M:$M,$A8,Serviços!$L:$L,"<>Cancelado",Serviços!$L:$L,"<>Retirado do Escopo",Serviços!$L:$L,"<>Substituído"))
A9: =IF($B9="","","SUB-"&TEXT(ROW()-1,"0000")) | E9: =IF($C9="","",INDEX(Etapas!$A:$A,MATCH($C9,Etapas!$B:$B,0))) | F9: =IF($B9="","",SUMIFS(Serviços!$J:$J,Serviços!$M:$M,$A9,Serviços!$L:$L,"<>Cancelado",Serviços!$L:$L,"<>Retirado do Escopo",Serviços!$L:$L,"<>Substituído"))
A10: =IF($B10="","","SUB-"&TEXT(ROW()-1,"0000")) | E10: =IF($C10="","",INDEX(Etapas!$A:$A,MATCH($C10,Etapas!$B:$B,0))) | F10: =IF($B10="","",SUMIFS(Serviços!$J:$J,Serviços!$M:$M,$A10,Serviços!$L:$L,"<>Cancelado",Serviços!$L:$L,"<>Retirado do Escopo",Serviços!$L:$L,"<>Substituído"))
A11: =IF($B11="","","SUB-"&TEXT(ROW()-1,"0000")) | E11: =IF($C11="","",INDEX(Etapas!$A:$A,MATCH($C11,Etapas!$B:$B,0))) | F11: =IF($B11="","",SUMIFS(Serviços!$J:$J,Serviços!$M:$M,$A11,Serviços!$L:$L,"<>Cancelado",Serviços!$L:$L,"<>Retirado do Escopo",Serviços!$L:$L,"<>Substituído"))
A12: =IF($B12="","","SUB-"&TEXT(ROW()-1,"0000")) | E12: =IF($C12="","",INDEX(Etapas!$A:$A,MATCH($C12,Etapas!$B:$B,0))) | F12: =IF($B12="","",SUMIFS(Serviços!$J:$J,Serviços!$M:$M,$A12,Serviços!$L:$L,"<>Cancelado",Serviços!$L:$L,"<>Retirado do Escopo",Serviços!$L:$L,"<>Substituído"))
A13: =IF($B13="","","SUB-"&TEXT(ROW()-1,"0000")) | E13: =IF($C13="","",INDEX(Etapas!$A:$A,MATCH($C13,Etapas!$B:$B,0))) | F13: =IF($B13="","",SUMIFS(Serviços!$J:$J,Serviços!$M:$M,$A13,Serviços!$L:$L,"<>Cancelado",Serviços!$L:$L,"<>Retirado do Escopo",Serviços!$L:$L,"<>Substituído"))
... A31: =IF($B31="","","SUB-"&TEXT(ROW()-1,"0000")) | E31: =IF($C31="","",INDEX(Etapas!$A:$A,MATCH($C31,Etapas!$B:$B,0))) | F31: =IF($B31="","",SUMIFS(Serviços!$J:$J,Serviços!$M:$M,$A31,Serviços!$L:$L,"<>Cancelado",Serviços!$L:$L,"<>Retirado do Escopo",Serviços!$L:$L,"<>Substituído"))

Sheet Serviços
A1: ID (técnico) | B1: Descrição | C1: Subetapa | D1: Unidade de Medida | E1: Quantidade Orçada | F1: Valor Unitário | G1: Valor Calculado | H1: Valor Previsto (Ajuste Manual) | I1: Ajuste Manual | J1: Valor Previsto | K1: Variação | L1: Status | M1: ID_Subetapa (técnico)
A2: =IF($B2="","","SRV-"&TEXT(ROW()-1,"0000")) | G2: =IF(OR($E2="",$F2=""),"",$E2*$F2) | I2: =IF($H2="","NÃO","SIM") | J2: =IF($H2="",$G2,$H2) | K2: =IF(OR($J2="",$G2=""),"",$J2-$G2) | M2: =IF($C2="","",INDEX(Subetapas!$A:$A,MATCH($C2,Subetapas!$B:$B,0)))
A3: =IF($B3="","","SRV-"&TEXT(ROW()-1,"0000")) | G3: =IF(OR($E3="",$F3=""),"",$E3*$F3) | I3: =IF($H3="","NÃO","SIM") | J3: =IF($H3="",$G3,$H3) | K3: =IF(OR($J3="",$G3=""),"",$J3-$G3) | M3: =IF($C3="","",INDEX(Subetapas!$A:$A,MATCH($C3,Subetapas!$B:$B,0)))
A4: =IF($B4="","","SRV-"&TEXT(ROW()-1,"0000")) | G4: =IF(OR($E4="",$F4=""),"",$E4*$F4) | I4: =IF($H4="","NÃO","SIM") | J4: =IF($H4="",$G4,$H4) | K4: =IF(OR($J4="",$G4=""),"",$J4-$G4) | M4: =IF($C4="","",INDEX(Subetapas!$A:$A,MATCH($C4,Subetapas!$B:$B,0)))
A5: =IF($B5="","","SRV-"&TEXT(ROW()-1,"0000")) | G5: =IF(OR($E5="",$F5=""),"",$E5*$F5) | I5: =IF($H5="","NÃO","SIM") | J5: =IF($H5="",$G5,$H5) | K5: =IF(OR($J5="",$G5=""),"",$J5-$G5) | M5: =IF($C5="","",INDEX(Subetapas!$A:$A,MATCH($C5,Subetapas!$B:$B,0)))
A6: =IF($B6="","","SRV-"&TEXT(ROW()-1,"0000")) | G6: =IF(OR($E6="",$F6=""),"",$E6*$F6) | I6: =IF($H6="","NÃO","SIM") | J6: =IF($H6="",$G6,$H6) | K6: =IF(OR($J6="",$G6=""),"",$J6-$G6) | M6: =IF($C6="","",INDEX(Subetapas!$A:$A,MATCH($C6,Subetapas!$B:$B,0)))
A7: =IF($B7="","","SRV-"&TEXT(ROW()-1,"0000")) | G7: =IF(OR($E7="",$F7=""),"",$E7*$F7) | I7: =IF($H7="","NÃO","SIM") | J7: =IF($H7="",$G7,$H7) | K7: =IF(OR($J7="",$G7=""),"",$J7-$G7) | M7: =IF($C7="","",INDEX(Subetapas!$A:$A,MATCH($C7,Subetapas!$B:$B,0)))
A8: =IF($B8="","","SRV-"&TEXT(ROW()-1,"0000")) | G8: =IF(OR($E8="",$F8=""),"",$E8*$F8) | I8: =IF($H8="","NÃO","SIM") | J8: =IF($H8="",$G8,$H8) | K8: =IF(OR($J8="",$G8=""),"",$J8-$G8) | M8: =IF($C8="","",INDEX(Subetapas!$A:$A,MATCH($C8,Subetapas!$B:$B,0)))
A9: =IF($B9="","","SRV-"&TEXT(ROW()-1,"0000")) | G9: =IF(OR($E9="",$F9=""),"",$E9*$F9) | I9: =IF($H9="","NÃO","SIM") | J9: =IF($H9="",$G9,$H9) | K9: =IF(OR($J9="",$G9=""),"",$J9-$G9) | M9: =IF($C9="","",INDEX(Subetapas!$A:$A,MATCH($C9,Subetapas!$B:$B,0)))
A10: =IF($B10="","","SRV-"&TEXT(ROW()-1,"0000")) | G10: =IF(OR($E10="",$F10=""),"",$E10*$F10) | I10: =IF($H10="","NÃO","SIM") | J10: =IF($H10="",$G10,$H10) | K10: =IF(OR($J10="",$G10=""),"",$J10-$G10) | M10: =IF($C10="","",INDEX(Subetapas!$A:$A,MATCH($C10,Subetapas!$B:$B,0)))
A11: =IF($B11="","","SRV-"&TEXT(ROW()-1,"0000")) | G11: =IF(OR($E11="",$F11=""),"",$E11*$F11) | I11: =IF($H11="","NÃO","SIM") | J11: =IF($H11="",$G11,$H11) | K11: =IF(OR($J11="",$G11=""),"",$J11-$G11) | M11: =IF($C11="","",INDEX(Subetapas!$A:$A,MATCH($C11,Subetapas!$B:$B,0)))
A12: =IF($B12="","","SRV-"&TEXT(ROW()-1,"0000")) | G12: =IF(OR($E12="",$F12=""),"",$E12*$F12) | I12: =IF($H12="","NÃO","SIM") | J12: =IF($H12="",$G12,$H12) | K12: =IF(OR($J12="",$G12=""),"",$J12-$G12) | M12: =IF($C12="","",INDEX(Subetapas!$A:$A,MATCH($C12,Subetapas!$B:$B,0)))
A13: =IF($B13="","","SRV-"&TEXT(ROW()-1,"0000")) | G13: =IF(OR($E13="",$F13=""),"",$E13*$F13) | I13: =IF($H13="","NÃO","SIM") | J13: =IF($H13="",$G13,$H13) | K13: =IF(OR($J13="",$G13=""),"",$J13-$G13) | M13: =IF($C13="","",INDEX(Subetapas!$A:$A,MATCH($C13,Subetapas!$B:$B,0)))
... A31: =IF($B31="","","SRV-"&TEXT(ROW()-1,"0000")) | G31: =IF(OR($E31="",$F31=""),"",$E31*$F31) | I31: =IF($H31="","NÃO","SIM") | J31: =IF($H31="",$G31,$H31) | K31: =IF(OR($J31="",$G31=""),"",$J31-$G31) | M31: =IF($C31="","",INDEX(Subetapas!$A:$A,MATCH($C31,Subetapas!$B:$B,0)))

Sheet Financeiro
A1: ID (técnico) | B1: Tipo | C1: Data | D1: Descrição | E1: Valor | F1: Entrada/Saída | G1: Aporte | H1: Custo Realizado | I1: Total Pago | J1: A Pagar | K1: Situação | L1: Observação | M1: ID_Obra (técnico)
A2: =IF($B2="","","FIN-"&TEXT(ROW()-1,"0000")) | F2: =IF($B2="","",IF($B2="Aporte","Entrada",IF($B2="Outras Entradas","Entrada",IF($B2="Outras Saídas","Saída","Custo (Caixa só no Pagamento)")))) | G2: =IF($B2="Aporte",$E2,"") | H2: =IF($B2="Despesa/Custo",$E2,"") | I2: =IF($B2="Despesa/Custo",SUMIFS(Pagamentos!$D:$D,Pagamentos!$F:$F,$A2),"") | J2: =IF($B2="Despesa/Custo",$H2-$I2,"") | M2: =IF($B2="","",Base_Dados!$B$2)
A3: =IF($B3="","","FIN-"&TEXT(ROW()-1,"0000")) | F3: =IF($B3="","",IF($B3="Aporte","Entrada",IF($B3="Outras Entradas","Entrada",IF($B3="Outras Saídas","Saída","Custo (Caixa só no Pagamento)")))) | G3: =IF($B3="Aporte",$E3,"") | H3: =IF($B3="Despesa/Custo",$E3,"") | I3: =IF($B3="Despesa/Custo",SUMIFS(Pagamentos!$D:$D,Pagamentos!$F:$F,$A3),"") | J3: =IF($B3="Despesa/Custo",$H3-$I3,"") | M3: =IF($B3="","",Base_Dados!$B$2)
A4: =IF($B4="","","FIN-"&TEXT(ROW()-1,"0000")) | F4: =IF($B4="","",IF($B4="Aporte","Entrada",IF($B4="Outras Entradas","Entrada",IF($B4="Outras Saídas","Saída","Custo (Caixa só no Pagamento)")))) | G4: =IF($B4="Aporte",$E4,"") | H4: =IF($B4="Despesa/Custo",$E4,"") | I4: =IF($B4="Despesa/Custo",SUMIFS(Pagamentos!$D:$D,Pagamentos!$F:$F,$A4),"") | J4: =IF($B4="Despesa/Custo",$H4-$I4,"") | M4: =IF($B4="","",Base_Dados!$B$2)
A5: =IF($B5="","","FIN-"&TEXT(ROW()-1,"0000")) | F5: =IF($B5="","",IF($B5="Aporte","Entrada",IF($B5="Outras Entradas","Entrada",IF($B5="Outras Saídas","Saída","Custo (Caixa só no Pagamento)")))) | G5: =IF($B5="Aporte",$E5,"") | H5: =IF($B5="Despesa/Custo",$E5,"") | I5: =IF($B5="Despesa/Custo",SUMIFS(Pagamentos!$D:$D,Pagamentos!$F:$F,$A5),"") | J5: =IF($B5="Despesa/Custo",$H5-$I5,"") | M5: =IF($B5="","",Base_Dados!$B$2)
A6: =IF($B6="","","FIN-"&TEXT(ROW()-1,"0000")) | F6: =IF($B6="","",IF($B6="Aporte","Entrada",IF($B6="Outras Entradas","Entrada",IF($B6="Outras Saídas","Saída","Custo (Caixa só no Pagamento)")))) | G6: =IF($B6="Aporte",$E6,"") | H6: =IF($B6="Despesa/Custo",$E6,"") | I6: =IF($B6="Despesa/Custo",SUMIFS(Pagamentos!$D:$D,Pagamentos!$F:$F,$A6),"") | J6: =IF($B6="Despesa/Custo",$H6-$I6,"") | M6: =IF($B6="","",Base_Dados!$B$2)
A7: =IF($B7="","","FIN-"&TEXT(ROW()-1,"0000")) | F7: =IF($B7="","",IF($B7="Aporte","Entrada",IF($B7="Outras Entradas","Entrada",IF($B7="Outras Saídas","Saída","Custo (Caixa só no Pagamento)")))) | G7: =IF($B7="Aporte",$E7,"") | H7: =IF($B7="Despesa/Custo",$E7,"") | I7: =IF($B7="Despesa/Custo",SUMIFS(Pagamentos!$D:$D,Pagamentos!$F:$F,$A7),"") | J7: =IF($B7="Despesa/Custo",$H7-$I7,"") | M7: =IF($B7="","",Base_Dados!$B$2)
A8: =IF($B8="","","FIN-"&TEXT(ROW()-1,"0000")) | F8: =IF($B8="","",IF($B8="Aporte","Entrada",IF($B8="Outras Entradas","Entrada",IF($B8="Outras Saídas","Saída","Custo (Caixa só no Pagamento)")))) | G8: =IF($B8="Aporte",$E8,"") | H8: =IF($B8="Despesa/Custo",$E8,"") | I8: =IF($B8="Despesa/Custo",SUMIFS(Pagamentos!$D:$D,Pagamentos!$F:$F,$A8),"") | J8: =IF($B8="Despesa/Custo",$H8-$I8,"") | M8: =IF($B8="","",Base_Dados!$B$2)
A9: =IF($B9="","","FIN-"&TEXT(ROW()-1,"0000")) | F9: =IF($B9="","",IF($B9="Aporte","Entrada",IF($B9="Outras Entradas","Entrada",IF($B9="Outras Saídas","Saída","Custo (Caixa só no Pagamento)")))) | G9: =IF($B9="Aporte",$E9,"") | H9: =IF($B9="Despesa/Custo",$E9,"") | I9: =IF($B9="Despesa/Custo",SUMIFS(Pagamentos!$D:$D,Pagamentos!$F:$F,$A9),"") | J9: =IF($B9="Despesa/Custo",$H9-$I9,"") | M9: =IF($B9="","",Base_Dados!$B$2)
A10: =IF($B10="","","FIN-"&TEXT(ROW()-1,"0000")) | F10: =IF($B10="","",IF($B10="Aporte","Entrada",IF($B10="Outras Entradas","Entrada",IF($B10="Outras Saídas","Saída","Custo (Caixa só no Pagamento)")))) | G10: =IF($B10="Aporte",$E10,"") | H10: =IF($B10="Despesa/Custo",$E10,"") | I10: =IF($B10="Despesa/Custo",SUMIFS(Pagamentos!$D:$D,Pagamentos!$F:$F,$A10),"") | J10: =IF($B10="Despesa/Custo",$H10-$I10,"") | M10: =IF($B10="","",Base_Dados!$B$2)
A11: =IF($B11="","","FIN-"&TEXT(ROW()-1,"0000")) | F11: =IF($B11="","",IF($B11="Aporte","Entrada",IF($B11="Outras Entradas","Entrada",IF($B11="Outras Saídas","Saída","Custo (Caixa só no Pagamento)")))) | G11: =IF($B11="Aporte",$E11,"") | H11: =IF($B11="Despesa/Custo",$E11,"") | I11: =IF($B11="Despesa/Custo",SUMIFS(Pagamentos!$D:$D,Pagamentos!$F:$F,$A11),"") | J11: =IF($B11="Despesa/Custo",$H11-$I11,"") | M11: =IF($B11="","",Base_Dados!$B$2)
A12: =IF($B12="","","FIN-"&TEXT(ROW()-1,"0000")) | F12: =IF($B12="","",IF($B12="Aporte","Entrada",IF($B12="Outras Entradas","Entrada",IF($B12="Outras Saídas","Saída","Custo (Caixa só no Pagamento)")))) | G12: =IF($B12="Aporte",$E12,"") | H12: =IF($B12="Despesa/Custo",$E12,"") | I12: =IF($B12="Despesa/Custo",SUMIFS(Pagamentos!$D:$D,Pagamentos!$F:$F,$A12),"") | J12: =IF($B12="Despesa/Custo",$H12-$I12,"") | M12: =IF($B12="","",Base_Dados!$B$2)
A13: =IF($B13="","","FIN-"&TEXT(ROW()-1,"0000")) | F13: =IF($B13="","",IF($B13="Aporte","Entrada",IF($B13="Outras Entradas","Entrada",IF($B13="Outras Saídas","Saída","Custo (Caixa só no Pagamento)")))) | G13: =IF($B13="Aporte",$E13,"") | H13: =IF($B13="Despesa/Custo",$E13,"") | I13: =IF($B13="Despesa/Custo",SUMIFS(Pagamentos!$D:$D,Pagamentos!$F:$F,$A13),"") | J13: =IF($B13="Despesa/Custo",$H13-$I13,"") | M13: =IF($B13="","",Base_Dados!$B$2)
... A31: =IF($B31="","","FIN-"&TEXT(ROW()-1,"0000")) | F31: =IF($B31="","",IF($B31="Aporte","Entrada",IF($B31="Outras Entradas","Entrada",IF($B31="Outras Saídas","Saída","Custo (Caixa só no Pagamento)")))) | G31: =IF($B31="Aporte",$E31,"") | H31: =IF($B31="Despesa/Custo",$E31,"") | I31: =IF($B31="Despesa/Custo",SUMIFS(Pagamentos!$D:$D,Pagamentos!$F:$F,$A31),"") | J31: =IF($B31="Despesa/Custo",$H31-$I31,"") | M31: =IF($B31="","",Base_Dados!$B$2)

Sheet Pagamentos
A1: ID (técnico) | B1: Lançamento (Despesa/Custo) | C1: Data do Pagamento | D1: Valor Pago | E1: Observação | F1: ID_Financeiro (técnico)
A2: =IF($B2="","","PGT-"&TEXT(ROW()-1,"0000")) | F2: =IF($B2="","",INDEX(Financeiro!$A:$A,MATCH($B2,Financeiro!$D:$D,0)))
A3: =IF($B3="","","PGT-"&TEXT(ROW()-1,"0000")) | F3: =IF($B3="","",INDEX(Financeiro!$A:$A,MATCH($B3,Financeiro!$D:$D,0)))
A4: =IF($B4="","","PGT-"&TEXT(ROW()-1,"0000")) | F4: =IF($B4="","",INDEX(Financeiro!$A:$A,MATCH($B4,Financeiro!$D:$D,0)))
A5: =IF($B5="","","PGT-"&TEXT(ROW()-1,"0000")) | F5: =IF($B5="","",INDEX(Financeiro!$A:$A,MATCH($B5,Financeiro!$D:$D,0)))
A6: =IF($B6="","","PGT-"&TEXT(ROW()-1,"0000")) | F6: =IF($B6="","",INDEX(Financeiro!$A:$A,MATCH($B6,Financeiro!$D:$D,0)))
A7: =IF($B7="","","PGT-"&TEXT(ROW()-1,"0000")) | F7: =IF($B7="","",INDEX(Financeiro!$A:$A,MATCH($B7,Financeiro!$D:$D,0)))
A8: =IF($B8="","","PGT-"&TEXT(ROW()-1,"0000")) | F8: =IF($B8="","",INDEX(Financeiro!$A:$A,MATCH($B8,Financeiro!$D:$D,0)))
A9: =IF($B9="","","PGT-"&TEXT(ROW()-1,"0000")) | F9: =IF($B9="","",INDEX(Financeiro!$A:$A,MATCH($B9,Financeiro!$D:$D,0)))
A10: =IF($B10="","","PGT-"&TEXT(ROW()-1,"0000")) | F10: =IF($B10="","",INDEX(Financeiro!$A:$A,MATCH($B10,Financeiro!$D:$D,0)))
A11: =IF($B11="","","PGT-"&TEXT(ROW()-1,"0000")) | F11: =IF($B11="","",INDEX(Financeiro!$A:$A,MATCH($B11,Financeiro!$D:$D,0)))
A12: =IF($B12="","","PGT-"&TEXT(ROW()-1,"0000")) | F12: =IF($B12="","",INDEX(Financeiro!$A:$A,MATCH($B12,Financeiro!$D:$D,0)))
A13: =IF($B13="","","PGT-"&TEXT(ROW()-1,"0000")) | F13: =IF($B13="","",INDEX(Financeiro!$A:$A,MATCH($B13,Financeiro!$D:$D,0)))
... A31: =IF($B31="","","PGT-"&TEXT(ROW()-1,"0000")) | F31: =IF($B31="","",INDEX(Financeiro!$A:$A,MATCH($B31,Financeiro!$D:$D,0)))

Sheet Resumo Financeiro
A1: Resumo Financeiro
A2: Orçamento Inicial (Previsto) | B2: =Início!$B$8
A3: Aportes | B3: =SUM(Financeiro!$G$2:$G$31)
A4: Orçamento Vigente | B4: =B2+B3
A5: Custo Realizado | B5: =SUM(Financeiro!$H$2:$H$31)
A6: Saldo Orçamentário | B6: =B4-B5
A7: % Orçamento Consumido | B7: =IF(B4=0,"N/D",B5/B4)
A8: Outras Entradas | B8: =SUMIF(Financeiro!$B$2:$B$31,"Outras Entradas",Financeiro!$E$2:$E$31)
A9: Outras Saídas | B9: =SUMIF(Financeiro!$B$2:$B$31,"Outras Saídas",Financeiro!$E$2:$E$31)
A10: Total de Entradas | B10: =B3+B8
A11: Total Pago | B11: =SUM(Financeiro!$I$2:$I$31)
A12: Total de Saídas | B12: =B11+B9
A13: Saldo de Caixa | B13: =B10-B12
A14: Total A Pagar | B14: =SUM(Financeiro!$J$2:$J$31)
A15: Estouro de Orçamento (indicador Operador-only) | B15: =IF(B6<0,"SIM","NÃO")
A17: Nota: Alterações Aprovadas ainda não integradas (Seção 4) — Orçamento Vigente considera apenas Orçamento Inicial + Aportes.
A18: Nota: 'Estouro de Orçamento' é Operador-only por especificação (Seções 29/30) — o mecanismo técnico de restrição por perfil ainda não existe (SEC_001, [H]).

Sheet Base_Dados
A1: Metadados internos — não editar
A2: ID da Obra (técnico) | B2: OBR-0001
A4: Prefixos de ID técnico homologados (ver Etapa 1, Seção 7)
A5: OBRAS | B5: OBR
A6: ETAPAS | B6: ETA
A7: SUBETAPAS | B7: SUB
A8: SERVICOS_ORCAMENTO | B8: SRV
A9: PLANEJAMENTO | B9: PLN
A10: FORNECEDORES | B10: FOR
A11: COMPRAS | B11: COM
A12: FINANCEIRO | B12: FIN
A13: EXECUCAO_MEDICOES | B13: EXE
A14: ALTERACOES | B14: ALT
A15: PENDENCIAS | B15: PEN
A16: ATUALIZACOES | B16: ATU
... A18: PAGAMENTOS | B18: PGT
A20: Status do Serviço homologados (Etapa 3, Seção 18)
A21: Ativo | B21: integra orçamento corrente
A22: Concluído | B22: integra orçamento corrente
A23: Cancelado | B23: excluído do orçamento corrente
A24: Retirado do Escopo | B24: excluído do orçamento corrente
A25: Substituído | B25: excluído do orçamento corrente
