Workbook
Name Lista_Etapas: TabelaEtapas[Nome]
Name Lista_Subetapas: TabelaSubetapas[Nome]
Name Lista_Financeiro_Descricoes: TabelaFinanceiro[Descrição]
Name Lista_Servicos: TabelaServicos[Descrição]

Sheet Início
A1: Dados da Obra
A2: Nome da Obra
A3: Cliente/Contratante
A4: Endereço
A5: Responsável Técnico
A6: Data Inicial Planejada
A7: Data Final Planejada
A8: Orçamento Inicial (Previsto) | B8: =SUM(TabelaEtapas[Total Previsto (Subetapas)])
A9: % Execução Física da Obra | B9: =IF(SUMPRODUCT(ISNUMBER(TabelaServicos[Valor Previsto])*(TabelaServicos[Status]<>"Cancelado")*(TabelaServicos[Status]<>"Retirado do Escopo")*(TabelaServicos[Status]<>"Substituído"))=0,"N/D",SUM(TabelaEtapas[Contribuição na Obra (Execução)]))
A10: Início Previsto (menor data das Etapas) | B10: =IF(COUNT(TabelaEtapas[Data Início Prevista])=0,"",MIN(TabelaEtapas[Data Início Prevista]))
A11: Fim Previsto (maior data das Etapas) | B11: =IF(COUNT(TabelaEtapas[Data Fim Prevista])=0,"",MAX(TabelaEtapas[Data Fim Prevista]))

Sheet Etapas
A1: ID (técnico) | B1: Nome | C1: Ordem | D1: Status | E1: ID_Obra (técnico) | F1: Total Previsto (Subetapas) | G1: Peso Consolidado (Execução) | H1: Contribuição na Obra (Execução) | I1: Data Início Prevista | J1: Data Fim Prevista | K1: Data Início Real | L1: Data Fim Real | M1: Duração Prevista (dias) | N1: Duração Real (dias) | O1: Variação de Prazo (dias)
A2: =IF($B2="","","ETA-"&TEXT(ROW()-1,"0000")) | E2: =IF($B2="","",Base_Dados!$B$2) | F2: =IF($B2="","",SUMIFS(Subetapas!$F:$F,Subetapas!$E:$E,$A2)) | G2: =IF($B2="","",SUMIFS(Subetapas!$G:$G,Subetapas!$E:$E,$A2)) | H2: =IF($B2="","",SUMIFS(Subetapas!$H:$H,Subetapas!$E:$E,$A2)) | M2: =IF(OR($I2="",$J2=""),"",$J2-$I2) | N2: =IF(OR($K2="",$L2=""),"",$L2-$K2) | O2: =IF(OR($J2="",$L2=""),"",$L2-$J2)
A3: =IF($B3="","","ETA-"&TEXT(ROW()-1,"0000")) | E3: =IF($B3="","",Base_Dados!$B$2) | F3: =IF($B3="","",SUMIFS(Subetapas!$F:$F,Subetapas!$E:$E,$A3)) | G3: =IF($B3="","",SUMIFS(Subetapas!$G:$G,Subetapas!$E:$E,$A3)) | H3: =IF($B3="","",SUMIFS(Subetapas!$H:$H,Subetapas!$E:$E,$A3)) | M3: =IF(OR($I3="",$J3=""),"",$J3-$I3) | N3: =IF(OR($K3="",$L3=""),"",$L3-$K3) | O3: =IF(OR($J3="",$L3=""),"",$L3-$J3)
A4: =IF($B4="","","ETA-"&TEXT(ROW()-1,"0000")) | E4: =IF($B4="","",Base_Dados!$B$2) | F4: =IF($B4="","",SUMIFS(Subetapas!$F:$F,Subetapas!$E:$E,$A4)) | G4: =IF($B4="","",SUMIFS(Subetapas!$G:$G,Subetapas!$E:$E,$A4)) | H4: =IF($B4="","",SUMIFS(Subetapas!$H:$H,Subetapas!$E:$E,$A4)) | M4: =IF(OR($I4="",$J4=""),"",$J4-$I4) | N4: =IF(OR($K4="",$L4=""),"",$L4-$K4) | O4: =IF(OR($J4="",$L4=""),"",$L4-$J4)
A5: =IF($B5="","","ETA-"&TEXT(ROW()-1,"0000")) | E5: =IF($B5="","",Base_Dados!$B$2) | F5: =IF($B5="","",SUMIFS(Subetapas!$F:$F,Subetapas!$E:$E,$A5)) | G5: =IF($B5="","",SUMIFS(Subetapas!$G:$G,Subetapas!$E:$E,$A5)) | H5: =IF($B5="","",SUMIFS(Subetapas!$H:$H,Subetapas!$E:$E,$A5)) | M5: =IF(OR($I5="",$J5=""),"",$J5-$I5) | N5: =IF(OR($K5="",$L5=""),"",$L5-$K5) | O5: =IF(OR($J5="",$L5=""),"",$L5-$J5)
A6: =IF($B6="","","ETA-"&TEXT(ROW()-1,"0000")) | E6: =IF($B6="","",Base_Dados!$B$2) | F6: =IF($B6="","",SUMIFS(Subetapas!$F:$F,Subetapas!$E:$E,$A6)) | G6: =IF($B6="","",SUMIFS(Subetapas!$G:$G,Subetapas!$E:$E,$A6)) | H6: =IF($B6="","",SUMIFS(Subetapas!$H:$H,Subetapas!$E:$E,$A6)) | M6: =IF(OR($I6="",$J6=""),"",$J6-$I6) | N6: =IF(OR($K6="",$L6=""),"",$L6-$K6) | O6: =IF(OR($J6="",$L6=""),"",$L6-$J6)
A7: =IF($B7="","","ETA-"&TEXT(ROW()-1,"0000")) | E7: =IF($B7="","",Base_Dados!$B$2) | F7: =IF($B7="","",SUMIFS(Subetapas!$F:$F,Subetapas!$E:$E,$A7)) | G7: =IF($B7="","",SUMIFS(Subetapas!$G:$G,Subetapas!$E:$E,$A7)) | H7: =IF($B7="","",SUMIFS(Subetapas!$H:$H,Subetapas!$E:$E,$A7)) | M7: =IF(OR($I7="",$J7=""),"",$J7-$I7) | N7: =IF(OR($K7="",$L7=""),"",$L7-$K7) | O7: =IF(OR($J7="",$L7=""),"",$L7-$J7)
A8: =IF($B8="","","ETA-"&TEXT(ROW()-1,"0000")) | E8: =IF($B8="","",Base_Dados!$B$2) | F8: =IF($B8="","",SUMIFS(Subetapas!$F:$F,Subetapas!$E:$E,$A8)) | G8: =IF($B8="","",SUMIFS(Subetapas!$G:$G,Subetapas!$E:$E,$A8)) | H8: =IF($B8="","",SUMIFS(Subetapas!$H:$H,Subetapas!$E:$E,$A8)) | M8: =IF(OR($I8="",$J8=""),"",$J8-$I8) | N8: =IF(OR($K8="",$L8=""),"",$L8-$K8) | O8: =IF(OR($J8="",$L8=""),"",$L8-$J8)
A9: =IF($B9="","","ETA-"&TEXT(ROW()-1,"0000")) | E9: =IF($B9="","",Base_Dados!$B$2) | F9: =IF($B9="","",SUMIFS(Subetapas!$F:$F,Subetapas!$E:$E,$A9)) | G9: =IF($B9="","",SUMIFS(Subetapas!$G:$G,Subetapas!$E:$E,$A9)) | H9: =IF($B9="","",SUMIFS(Subetapas!$H:$H,Subetapas!$E:$E,$A9)) | M9: =IF(OR($I9="",$J9=""),"",$J9-$I9) | N9: =IF(OR($K9="",$L9=""),"",$L9-$K9) | O9: =IF(OR($J9="",$L9=""),"",$L9-$J9)
A10: =IF($B10="","","ETA-"&TEXT(ROW()-1,"0000")) | E10: =IF($B10="","",Base_Dados!$B$2) | F10: =IF($B10="","",SUMIFS(Subetapas!$F:$F,Subetapas!$E:$E,$A10)) | G10: =IF($B10="","",SUMIFS(Subetapas!$G:$G,Subetapas!$E:$E,$A10)) | H10: =IF($B10="","",SUMIFS(Subetapas!$H:$H,Subetapas!$E:$E,$A10)) | M10: =IF(OR($I10="",$J10=""),"",$J10-$I10) | N10: =IF(OR($K10="",$L10=""),"",$L10-$K10) | O10: =IF(OR($J10="",$L10=""),"",$L10-$J10)
A11: =IF($B11="","","ETA-"&TEXT(ROW()-1,"0000")) | E11: =IF($B11="","",Base_Dados!$B$2) | F11: =IF($B11="","",SUMIFS(Subetapas!$F:$F,Subetapas!$E:$E,$A11)) | G11: =IF($B11="","",SUMIFS(Subetapas!$G:$G,Subetapas!$E:$E,$A11)) | H11: =IF($B11="","",SUMIFS(Subetapas!$H:$H,Subetapas!$E:$E,$A11)) | M11: =IF(OR($I11="",$J11=""),"",$J11-$I11) | N11: =IF(OR($K11="",$L11=""),"",$L11-$K11) | O11: =IF(OR($J11="",$L11=""),"",$L11-$J11)
A12: =IF($B12="","","ETA-"&TEXT(ROW()-1,"0000")) | E12: =IF($B12="","",Base_Dados!$B$2) | F12: =IF($B12="","",SUMIFS(Subetapas!$F:$F,Subetapas!$E:$E,$A12)) | G12: =IF($B12="","",SUMIFS(Subetapas!$G:$G,Subetapas!$E:$E,$A12)) | H12: =IF($B12="","",SUMIFS(Subetapas!$H:$H,Subetapas!$E:$E,$A12)) | M12: =IF(OR($I12="",$J12=""),"",$J12-$I12) | N12: =IF(OR($K12="",$L12=""),"",$L12-$K12) | O12: =IF(OR($J12="",$L12=""),"",$L12-$J12)
A13: =IF($B13="","","ETA-"&TEXT(ROW()-1,"0000")) | E13: =IF($B13="","",Base_Dados!$B$2) | F13: =IF($B13="","",SUMIFS(Subetapas!$F:$F,Subetapas!$E:$E,$A13)) | G13: =IF($B13="","",SUMIFS(Subetapas!$G:$G,Subetapas!$E:$E,$A13)) | H13: =IF($B13="","",SUMIFS(Subetapas!$H:$H,Subetapas!$E:$E,$A13)) | M13: =IF(OR($I13="",$J13=""),"",$J13-$I13) | N13: =IF(OR($K13="",$L13=""),"",$L13-$K13) | O13: =IF(OR($J13="",$L13=""),"",$L13-$J13)
... A31: =IF($B31="","","ETA-"&TEXT(ROW()-1,"0000")) | E31: =IF($B31="","",Base_Dados!$B$2) | F31: =IF($B31="","",SUMIFS(Subetapas!$F:$F,Subetapas!$E:$E,$A31)) | G31: =IF($B31="","",SUMIFS(Subetapas!$G:$G,Subetapas!$E:$E,$A31)) | H31: =IF($B31="","",SUMIFS(Subetapas!$H:$H,Subetapas!$E:$E,$A31)) | M31: =IF(OR($I31="",$J31=""),"",$J31-$I31) | N31: =IF(OR($K31="",$L31=""),"",$L31-$K31) | O31: =IF(OR($J31="",$L31=""),"",$L31-$J31)

Sheet Subetapas
A1: ID (técnico) | B1: Nome | C1: Etapa | D1: Status | E1: ID_Etapa (técnico) | F1: Total Previsto (Serviços) | G1: Peso Consolidado (Execução) | H1: Contribuição na Obra (Execução) | I1: Data Início Prevista | J1: Data Fim Prevista | K1: Data Início Real | L1: Data Fim Real | M1: Duração Prevista (dias) | N1: Duração Real (dias) | O1: Variação de Prazo (dias)
A2: =IF($B2="","","SUB-"&TEXT(ROW()-1,"0000")) | E2: =IF($C2="","",INDEX(Etapas!$A:$A,MATCH($C2,Etapas!$B:$B,0))) | F2: =IF($B2="","",SUMIFS(Serviços!$J:$J,Serviços!$U:$U,$A2,Serviços!$L:$L,"<>Cancelado",Serviços!$L:$L,"<>Retirado do Escopo",Serviços!$L:$L,"<>Substituído")) | G2: =IF($B2="","",SUMIFS(Serviços!$S:$S,Serviços!$U:$U,$A2)) | H2: =IF($B2="","",SUMIFS(Serviços!$T:$T,Serviços!$U:$U,$A2)) | M2: =IF(OR($I2="",$J2=""),"",$J2-$I2) | N2: =IF(OR($K2="",$L2=""),"",$L2-$K2) | O2: =IF(OR($J2="",$L2=""),"",$L2-$J2)
A3: =IF($B3="","","SUB-"&TEXT(ROW()-1,"0000")) | E3: =IF($C3="","",INDEX(Etapas!$A:$A,MATCH($C3,Etapas!$B:$B,0))) | F3: =IF($B3="","",SUMIFS(Serviços!$J:$J,Serviços!$U:$U,$A3,Serviços!$L:$L,"<>Cancelado",Serviços!$L:$L,"<>Retirado do Escopo",Serviços!$L:$L,"<>Substituído")) | G3: =IF($B3="","",SUMIFS(Serviços!$S:$S,Serviços!$U:$U,$A3)) | H3: =IF($B3="","",SUMIFS(Serviços!$T:$T,Serviços!$U:$U,$A3)) | M3: =IF(OR($I3="",$J3=""),"",$J3-$I3) | N3: =IF(OR($K3="",$L3=""),"",$L3-$K3) | O3: =IF(OR($J3="",$L3=""),"",$L3-$J3)
A4: =IF($B4="","","SUB-"&TEXT(ROW()-1,"0000")) | E4: =IF($C4="","",INDEX(Etapas!$A:$A,MATCH($C4,Etapas!$B:$B,0))) | F4: =IF($B4="","",SUMIFS(Serviços!$J:$J,Serviços!$U:$U,$A4,Serviços!$L:$L,"<>Cancelado",Serviços!$L:$L,"<>Retirado do Escopo",Serviços!$L:$L,"<>Substituído")) | G4: =IF($B4="","",SUMIFS(Serviços!$S:$S,Serviços!$U:$U,$A4)) | H4: =IF($B4="","",SUMIFS(Serviços!$T:$T,Serviços!$U:$U,$A4)) | M4: =IF(OR($I4="",$J4=""),"",$J4-$I4) | N4: =IF(OR($K4="",$L4=""),"",$L4-$K4) | O4: =IF(OR($J4="",$L4=""),"",$L4-$J4)
A5: =IF($B5="","","SUB-"&TEXT(ROW()-1,"0000")) | E5: =IF($C5="","",INDEX(Etapas!$A:$A,MATCH($C5,Etapas!$B:$B,0))) | F5: =IF($B5="","",SUMIFS(Serviços!$J:$J,Serviços!$U:$U,$A5,Serviços!$L:$L,"<>Cancelado",Serviços!$L:$L,"<>Retirado do Escopo",Serviços!$L:$L,"<>Substituído")) | G5: =IF($B5="","",SUMIFS(Serviços!$S:$S,Serviços!$U:$U,$A5)) | H5: =IF($B5="","",SUMIFS(Serviços!$T:$T,Serviços!$U:$U,$A5)) | M5: =IF(OR($I5="",$J5=""),"",$J5-$I5) | N5: =IF(OR($K5="",$L5=""),"",$L5-$K5) | O5: =IF(OR($J5="",$L5=""),"",$L5-$J5)
A6: =IF($B6="","","SUB-"&TEXT(ROW()-1,"0000")) | E6: =IF($C6="","",INDEX(Etapas!$A:$A,MATCH($C6,Etapas!$B:$B,0))) | F6: =IF($B6="","",SUMIFS(Serviços!$J:$J,Serviços!$U:$U,$A6,Serviços!$L:$L,"<>Cancelado",Serviços!$L:$L,"<>Retirado do Escopo",Serviços!$L:$L,"<>Substituído")) | G6: =IF($B6="","",SUMIFS(Serviços!$S:$S,Serviços!$U:$U,$A6)) | H6: =IF($B6="","",SUMIFS(Serviços!$T:$T,Serviços!$U:$U,$A6)) | M6: =IF(OR($I6="",$J6=""),"",$J6-$I6) | N6: =IF(OR($K6="",$L6=""),"",$L6-$K6) | O6: =IF(OR($J6="",$L6=""),"",$L6-$J6)
A7: =IF($B7="","","SUB-"&TEXT(ROW()-1,"0000")) | E7: =IF($C7="","",INDEX(Etapas!$A:$A,MATCH($C7,Etapas!$B:$B,0))) | F7: =IF($B7="","",SUMIFS(Serviços!$J:$J,Serviços!$U:$U,$A7,Serviços!$L:$L,"<>Cancelado",Serviços!$L:$L,"<>Retirado do Escopo",Serviços!$L:$L,"<>Substituído")) | G7: =IF($B7="","",SUMIFS(Serviços!$S:$S,Serviços!$U:$U,$A7)) | H7: =IF($B7="","",SUMIFS(Serviços!$T:$T,Serviços!$U:$U,$A7)) | M7: =IF(OR($I7="",$J7=""),"",$J7-$I7) | N7: =IF(OR($K7="",$L7=""),"",$L7-$K7) | O7: =IF(OR($J7="",$L7=""),"",$L7-$J7)
A8: =IF($B8="","","SUB-"&TEXT(ROW()-1,"0000")) | E8: =IF($C8="","",INDEX(Etapas!$A:$A,MATCH($C8,Etapas!$B:$B,0))) | F8: =IF($B8="","",SUMIFS(Serviços!$J:$J,Serviços!$U:$U,$A8,Serviços!$L:$L,"<>Cancelado",Serviços!$L:$L,"<>Retirado do Escopo",Serviços!$L:$L,"<>Substituído")) | G8: =IF($B8="","",SUMIFS(Serviços!$S:$S,Serviços!$U:$U,$A8)) | H8: =IF($B8="","",SUMIFS(Serviços!$T:$T,Serviços!$U:$U,$A8)) | M8: =IF(OR($I8="",$J8=""),"",$J8-$I8) | N8: =IF(OR($K8="",$L8=""),"",$L8-$K8) | O8: =IF(OR($J8="",$L8=""),"",$L8-$J8)
A9: =IF($B9="","","SUB-"&TEXT(ROW()-1,"0000")) | E9: =IF($C9="","",INDEX(Etapas!$A:$A,MATCH($C9,Etapas!$B:$B,0))) | F9: =IF($B9="","",SUMIFS(Serviços!$J:$J,Serviços!$U:$U,$A9,Serviços!$L:$L,"<>Cancelado",Serviços!$L:$L,"<>Retirado do Escopo",Serviços!$L:$L,"<>Substituído")) | G9: =IF($B9="","",SUMIFS(Serviços!$S:$S,Serviços!$U:$U,$A9)) | H9: =IF($B9="","",SUMIFS(Serviços!$T:$T,Serviços!$U:$U,$A9)) | M9: =IF(OR($I9="",$J9=""),"",$J9-$I9) | N9: =IF(OR($K9="",$L9=""),"",$L9-$K9) | O9: =IF(OR($J9="",$L9=""),"",$L9-$J9)
A10: =IF($B10="","","SUB-"&TEXT(ROW()-1,"0000")) | E10: =IF($C10="","",INDEX(Etapas!$A:$A,MATCH($C10,Etapas!$B:$B,0))) | F10: =IF($B10="","",SUMIFS(Serviços!$J:$J,Serviços!$U:$U,$A10,Serviços!$L:$L,"<>Cancelado",Serviços!$L:$L,"<>Retirado do Escopo",Serviços!$L:$L,"<>Substituído")) | G10: =IF($B10="","",SUMIFS(Serviços!$S:$S,Serviços!$U:$U,$A10)) | H10: =IF($B10="","",SUMIFS(Serviços!$T:$T,Serviços!$U:$U,$A10)) | M10: =IF(OR($I10="",$J10=""),"",$J10-$I10) | N10: =IF(OR($K10="",$L10=""),"",$L10-$K10) | O10: =IF(OR($J10="",$L10=""),"",$L10-$J10)
A11: =IF($B11="","","SUB-"&TEXT(ROW()-1,"0000")) | E11: =IF($C11="","",INDEX(Etapas!$A:$A,MATCH($C11,Etapas!$B:$B,0))) | F11: =IF($B11="","",SUMIFS(Serviços!$J:$J,Serviços!$U:$U,$A11,Serviços!$L:$L,"<>Cancelado",Serviços!$L:$L,"<>Retirado do Escopo",Serviços!$L:$L,"<>Substituído")) | G11: =IF($B11="","",SUMIFS(Serviços!$S:$S,Serviços!$U:$U,$A11)) | H11: =IF($B11="","",SUMIFS(Serviços!$T:$T,Serviços!$U:$U,$A11)) | M11: =IF(OR($I11="",$J11=""),"",$J11-$I11) | N11: =IF(OR($K11="",$L11=""),"",$L11-$K11) | O11: =IF(OR($J11="",$L11=""),"",$L11-$J11)
A12: =IF($B12="","","SUB-"&TEXT(ROW()-1,"0000")) | E12: =IF($C12="","",INDEX(Etapas!$A:$A,MATCH($C12,Etapas!$B:$B,0))) | F12: =IF($B12="","",SUMIFS(Serviços!$J:$J,Serviços!$U:$U,$A12,Serviços!$L:$L,"<>Cancelado",Serviços!$L:$L,"<>Retirado do Escopo",Serviços!$L:$L,"<>Substituído")) | G12: =IF($B12="","",SUMIFS(Serviços!$S:$S,Serviços!$U:$U,$A12)) | H12: =IF($B12="","",SUMIFS(Serviços!$T:$T,Serviços!$U:$U,$A12)) | M12: =IF(OR($I12="",$J12=""),"",$J12-$I12) | N12: =IF(OR($K12="",$L12=""),"",$L12-$K12) | O12: =IF(OR($J12="",$L12=""),"",$L12-$J12)
A13: =IF($B13="","","SUB-"&TEXT(ROW()-1,"0000")) | E13: =IF($C13="","",INDEX(Etapas!$A:$A,MATCH($C13,Etapas!$B:$B,0))) | F13: =IF($B13="","",SUMIFS(Serviços!$J:$J,Serviços!$U:$U,$A13,Serviços!$L:$L,"<>Cancelado",Serviços!$L:$L,"<>Retirado do Escopo",Serviços!$L:$L,"<>Substituído")) | G13: =IF($B13="","",SUMIFS(Serviços!$S:$S,Serviços!$U:$U,$A13)) | H13: =IF($B13="","",SUMIFS(Serviços!$T:$T,Serviços!$U:$U,$A13)) | M13: =IF(OR($I13="",$J13=""),"",$J13-$I13) | N13: =IF(OR($K13="",$L13=""),"",$L13-$K13) | O13: =IF(OR($J13="",$L13=""),"",$L13-$J13)
... A31: =IF($B31="","","SUB-"&TEXT(ROW()-1,"0000")) | E31: =IF($C31="","",INDEX(Etapas!$A:$A,MATCH($C31,Etapas!$B:$B,0))) | F31: =IF($B31="","",SUMIFS(Serviços!$J:$J,Serviços!$U:$U,$A31,Serviços!$L:$L,"<>Cancelado",Serviços!$L:$L,"<>Retirado do Escopo",Serviços!$L:$L,"<>Substituído")) | G31: =IF($B31="","",SUMIFS(Serviços!$S:$S,Serviços!$U:$U,$A31)) | H31: =IF($B31="","",SUMIFS(Serviços!$T:$T,Serviços!$U:$U,$A31)) | M31: =IF(OR($I31="",$J31=""),"",$J31-$I31) | N31: =IF(OR($K31="",$L31=""),"",$L31-$K31) | O31: =IF(OR($J31="",$L31=""),"",$L31-$J31)

Sheet Serviços
A1: ID (técnico) | B1: Descrição | C1: Subetapa | D1: Unidade de Medida | E1: Quantidade Orçada | F1: Valor Unitário | G1: Valor Calculado | H1: Valor Previsto (Ajuste Manual) | I1: Ajuste Manual | J1: Valor Previsto | K1: Variação | L1: Status | M1: Método de Execução | N1: Status de Execução | O1: Qtd. Executada (acum.) | P1: % Execução do Serviço | Q1: Peso Ajustado (manual) | R1: Peso Automático | S1: Peso Efetivo | T1: Contribuição na Obra | U1: ID_Subetapa (técnico)
A2: =IF($B2="","","SRV-"&TEXT(ROW()-1,"0000")) | G2: =IF(OR($E2="",$F2=""),"",$E2*$F2) | I2: =IF($H2="","NÃO","SIM") | J2: =IF($H2="",$G2,$H2) | K2: =IF(OR($J2="",$G2=""),"",$J2-$G2) | O2: =IF($A2="","",SUMIFS(Execução!$D:$D,Execução!$F:$F,$A2)) | P2: =IF($A2="","",IF($M2="Quantitativo",IF(OR($E2="",$E2=0),"",$O2/$E2),IF($M2="Status",IF($N2="Pendente",0,IF($N2="Em andamento",0.5,IF($N2="Concluído",1,""))),""))) | R2: =IF(OR($A2="",$L2="Cancelado",$L2="Retirado do Escopo",$L2="Substituído",$J2=""),"",IF(SUMIFS($J:$J,$L:$L,"<>Cancelado",$L:$L,"<>Retirado do Escopo",$L:$L,"<>Substituído",$J:$J,"<>")=0,"N/D",$J2/SUMIFS($J:$J,$L:$L,"<>Cancelado",$L:$L,"<>Retirado do Escopo",$L:$L,"<>Substituído",$J:$J,"<>"))) | S2: =IF(OR($A2="",$L2="Cancelado",$L2="Retirado do Escopo",$L2="Substituído",$J2=""),"",IF($Q2<>"",$Q2,IF(SUMIFS($R:$R,$L:$L,"<>Cancelado",$L:$L,"<>Retirado do Escopo",$L:$L,"<>Substituído",$J:$J,"<>",$Q:$Q,"")=0,IF(SUMPRODUCT(ISNUMBER(TabelaServicos[Valor Previsto])*(TabelaServicos[Status]<>"Cancelado")*(TabelaServicos[Status]<>"Retirado do Escopo")*(TabelaServicos[Status]<>"Substituído")*(TabelaServicos[Peso Ajustado (manual)]=""))=0,"N/D",(1-SUMIFS($Q:$Q,$L:$L,"<>Cancelado",$L:$L,"<>Retirado do Escopo",$L:$L,"<>Substituído",$J:$J,"<>",$Q:$Q,"<>"))/SUMPRODUCT(ISNUMBER(TabelaServicos[Valor Previsto])*(TabelaServicos[Status]<>"Cancelado")*(TabelaServicos[Status]<>"Retirado do Escopo")*(TabelaServicos[Status]<>"Substituído")*(TabelaServicos[Peso Ajustado (manual)]=""))),$R2/SUMIFS($R:$R,$L:$L,"<>Cancelado",$L:$L,"<>Retirado do Escopo",$L:$L,"<>Substituído",$J:$J,"<>",$Q:$Q,"")*(1-SUMIFS($Q:$Q,$L:$L,"<>Cancelado",$L:$L,"<>Retirado do Escopo",$L:$L,"<>Substituído",$J:$J,"<>",$Q:$Q,"<>"))))) | T2: =IF(OR($S2="",$P2=""),"",$S2*$P2) | U2: =IF($C2="","",INDEX(Subetapas!$A:$A,MATCH($C2,Subetapas!$B:$B,0)))
A3: =IF($B3="","","SRV-"&TEXT(ROW()-1,"0000")) | G3: =IF(OR($E3="",$F3=""),"",$E3*$F3) | I3: =IF($H3="","NÃO","SIM") | J3: =IF($H3="",$G3,$H3) | K3: =IF(OR($J3="",$G3=""),"",$J3-$G3) | O3: =IF($A3="","",SUMIFS(Execução!$D:$D,Execução!$F:$F,$A3)) | P3: =IF($A3="","",IF($M3="Quantitativo",IF(OR($E3="",$E3=0),"",$O3/$E3),IF($M3="Status",IF($N3="Pendente",0,IF($N3="Em andamento",0.5,IF($N3="Concluído",1,""))),""))) | R3: =IF(OR($A3="",$L3="Cancelado",$L3="Retirado do Escopo",$L3="Substituído",$J3=""),"",IF(SUMIFS($J:$J,$L:$L,"<>Cancelado",$L:$L,"<>Retirado do Escopo",$L:$L,"<>Substituído",$J:$J,"<>")=0,"N/D",$J3/SUMIFS($J:$J,$L:$L,"<>Cancelado",$L:$L,"<>Retirado do Escopo",$L:$L,"<>Substituído",$J:$J,"<>"))) | S3: =IF(OR($A3="",$L3="Cancelado",$L3="Retirado do Escopo",$L3="Substituído",$J3=""),"",IF($Q3<>"",$Q3,IF(SUMIFS($R:$R,$L:$L,"<>Cancelado",$L:$L,"<>Retirado do Escopo",$L:$L,"<>Substituído",$J:$J,"<>",$Q:$Q,"")=0,IF(SUMPRODUCT(ISNUMBER(TabelaServicos[Valor Previsto])*(TabelaServicos[Status]<>"Cancelado")*(TabelaServicos[Status]<>"Retirado do Escopo")*(TabelaServicos[Status]<>"Substituído")*(TabelaServicos[Peso Ajustado (manual)]=""))=0,"N/D",(1-SUMIFS($Q:$Q,$L:$L,"<>Cancelado",$L:$L,"<>Retirado do Escopo",$L:$L,"<>Substituído",$J:$J,"<>",$Q:$Q,"<>"))/SUMPRODUCT(ISNUMBER(TabelaServicos[Valor Previsto])*(TabelaServicos[Status]<>"Cancelado")*(TabelaServicos[Status]<>"Retirado do Escopo")*(TabelaServicos[Status]<>"Substituído")*(TabelaServicos[Peso Ajustado (manual)]=""))),$R3/SUMIFS($R:$R,$L:$L,"<>Cancelado",$L:$L,"<>Retirado do Escopo",$L:$L,"<>Substituído",$J:$J,"<>",$Q:$Q,"")*(1-SUMIFS($Q:$Q,$L:$L,"<>Cancelado",$L:$L,"<>Retirado do Escopo",$L:$L,"<>Substituído",$J:$J,"<>",$Q:$Q,"<>"))))) | T3: =IF(OR($S3="",$P3=""),"",$S3*$P3) | U3: =IF($C3="","",INDEX(Subetapas!$A:$A,MATCH($C3,Subetapas!$B:$B,0)))
A4: =IF($B4="","","SRV-"&TEXT(ROW()-1,"0000")) | G4: =IF(OR($E4="",$F4=""),"",$E4*$F4) | I4: =IF($H4="","NÃO","SIM") | J4: =IF($H4="",$G4,$H4) | K4: =IF(OR($J4="",$G4=""),"",$J4-$G4) | O4: =IF($A4="","",SUMIFS(Execução!$D:$D,Execução!$F:$F,$A4)) | P4: =IF($A4="","",IF($M4="Quantitativo",IF(OR($E4="",$E4=0),"",$O4/$E4),IF($M4="Status",IF($N4="Pendente",0,IF($N4="Em andamento",0.5,IF($N4="Concluído",1,""))),""))) | R4: =IF(OR($A4="",$L4="Cancelado",$L4="Retirado do Escopo",$L4="Substituído",$J4=""),"",IF(SUMIFS($J:$J,$L:$L,"<>Cancelado",$L:$L,"<>Retirado do Escopo",$L:$L,"<>Substituído",$J:$J,"<>")=0,"N/D",$J4/SUMIFS($J:$J,$L:$L,"<>Cancelado",$L:$L,"<>Retirado do Escopo",$L:$L,"<>Substituído",$J:$J,"<>"))) | S4: =IF(OR($A4="",$L4="Cancelado",$L4="Retirado do Escopo",$L4="Substituído",$J4=""),"",IF($Q4<>"",$Q4,IF(SUMIFS($R:$R,$L:$L,"<>Cancelado",$L:$L,"<>Retirado do Escopo",$L:$L,"<>Substituído",$J:$J,"<>",$Q:$Q,"")=0,IF(SUMPRODUCT(ISNUMBER(TabelaServicos[Valor Previsto])*(TabelaServicos[Status]<>"Cancelado")*(TabelaServicos[Status]<>"Retirado do Escopo")*(TabelaServicos[Status]<>"Substituído")*(TabelaServicos[Peso Ajustado (manual)]=""))=0,"N/D",(1-SUMIFS($Q:$Q,$L:$L,"<>Cancelado",$L:$L,"<>Retirado do Escopo",$L:$L,"<>Substituído",$J:$J,"<>",$Q:$Q,"<>"))/SUMPRODUCT(ISNUMBER(TabelaServicos[Valor Previsto])*(TabelaServicos[Status]<>"Cancelado")*(TabelaServicos[Status]<>"Retirado do Escopo")*(TabelaServicos[Status]<>"Substituído")*(TabelaServicos[Peso Ajustado (manual)]=""))),$R4/SUMIFS($R:$R,$L:$L,"<>Cancelado",$L:$L,"<>Retirado do Escopo",$L:$L,"<>Substituído",$J:$J,"<>",$Q:$Q,"")*(1-SUMIFS($Q:$Q,$L:$L,"<>Cancelado",$L:$L,"<>Retirado do Escopo",$L:$L,"<>Substituído",$J:$J,"<>",$Q:$Q,"<>"))))) | T4: =IF(OR($S4="",$P4=""),"",$S4*$P4) | U4: =IF($C4="","",INDEX(Subetapas!$A:$A,MATCH($C4,Subetapas!$B:$B,0)))
A5: =IF($B5="","","SRV-"&TEXT(ROW()-1,"0000")) | G5: =IF(OR($E5="",$F5=""),"",$E5*$F5) | I5: =IF($H5="","NÃO","SIM") | J5: =IF($H5="",$G5,$H5) | K5: =IF(OR($J5="",$G5=""),"",$J5-$G5) | O5: =IF($A5="","",SUMIFS(Execução!$D:$D,Execução!$F:$F,$A5)) | P5: =IF($A5="","",IF($M5="Quantitativo",IF(OR($E5="",$E5=0),"",$O5/$E5),IF($M5="Status",IF($N5="Pendente",0,IF($N5="Em andamento",0.5,IF($N5="Concluído",1,""))),""))) | R5: =IF(OR($A5="",$L5="Cancelado",$L5="Retirado do Escopo",$L5="Substituído",$J5=""),"",IF(SUMIFS($J:$J,$L:$L,"<>Cancelado",$L:$L,"<>Retirado do Escopo",$L:$L,"<>Substituído",$J:$J,"<>")=0,"N/D",$J5/SUMIFS($J:$J,$L:$L,"<>Cancelado",$L:$L,"<>Retirado do Escopo",$L:$L,"<>Substituído",$J:$J,"<>"))) | S5: =IF(OR($A5="",$L5="Cancelado",$L5="Retirado do Escopo",$L5="Substituído",$J5=""),"",IF($Q5<>"",$Q5,IF(SUMIFS($R:$R,$L:$L,"<>Cancelado",$L:$L,"<>Retirado do Escopo",$L:$L,"<>Substituído",$J:$J,"<>",$Q:$Q,"")=0,IF(SUMPRODUCT(ISNUMBER(TabelaServicos[Valor Previsto])*(TabelaServicos[Status]<>"Cancelado")*(TabelaServicos[Status]<>"Retirado do Escopo")*(TabelaServicos[Status]<>"Substituído")*(TabelaServicos[Peso Ajustado (manual)]=""))=0,"N/D",(1-SUMIFS($Q:$Q,$L:$L,"<>Cancelado",$L:$L,"<>Retirado do Escopo",$L:$L,"<>Substituído",$J:$J,"<>",$Q:$Q,"<>"))/SUMPRODUCT(ISNUMBER(TabelaServicos[Valor Previsto])*(TabelaServicos[Status]<>"Cancelado")*(TabelaServicos[Status]<>"Retirado do Escopo")*(TabelaServicos[Status]<>"Substituído")*(TabelaServicos[Peso Ajustado (manual)]=""))),$R5/SUMIFS($R:$R,$L:$L,"<>Cancelado",$L:$L,"<>Retirado do Escopo",$L:$L,"<>Substituído",$J:$J,"<>",$Q:$Q,"")*(1-SUMIFS($Q:$Q,$L:$L,"<>Cancelado",$L:$L,"<>Retirado do Escopo",$L:$L,"<>Substituído",$J:$J,"<>",$Q:$Q,"<>"))))) | T5: =IF(OR($S5="",$P5=""),"",$S5*$P5) | U5: =IF($C5="","",INDEX(Subetapas!$A:$A,MATCH($C5,Subetapas!$B:$B,0)))
A6: =IF($B6="","","SRV-"&TEXT(ROW()-1,"0000")) | G6: =IF(OR($E6="",$F6=""),"",$E6*$F6) | I6: =IF($H6="","NÃO","SIM") | J6: =IF($H6="",$G6,$H6) | K6: =IF(OR($J6="",$G6=""),"",$J6-$G6) | O6: =IF($A6="","",SUMIFS(Execução!$D:$D,Execução!$F:$F,$A6)) | P6: =IF($A6="","",IF($M6="Quantitativo",IF(OR($E6="",$E6=0),"",$O6/$E6),IF($M6="Status",IF($N6="Pendente",0,IF($N6="Em andamento",0.5,IF($N6="Concluído",1,""))),""))) | R6: =IF(OR($A6="",$L6="Cancelado",$L6="Retirado do Escopo",$L6="Substituído",$J6=""),"",IF(SUMIFS($J:$J,$L:$L,"<>Cancelado",$L:$L,"<>Retirado do Escopo",$L:$L,"<>Substituído",$J:$J,"<>")=0,"N/D",$J6/SUMIFS($J:$J,$L:$L,"<>Cancelado",$L:$L,"<>Retirado do Escopo",$L:$L,"<>Substituído",$J:$J,"<>"))) | S6: =IF(OR($A6="",$L6="Cancelado",$L6="Retirado do Escopo",$L6="Substituído",$J6=""),"",IF($Q6<>"",$Q6,IF(SUMIFS($R:$R,$L:$L,"<>Cancelado",$L:$L,"<>Retirado do Escopo",$L:$L,"<>Substituído",$J:$J,"<>",$Q:$Q,"")=0,IF(SUMPRODUCT(ISNUMBER(TabelaServicos[Valor Previsto])*(TabelaServicos[Status]<>"Cancelado")*(TabelaServicos[Status]<>"Retirado do Escopo")*(TabelaServicos[Status]<>"Substituído")*(TabelaServicos[Peso Ajustado (manual)]=""))=0,"N/D",(1-SUMIFS($Q:$Q,$L:$L,"<>Cancelado",$L:$L,"<>Retirado do Escopo",$L:$L,"<>Substituído",$J:$J,"<>",$Q:$Q,"<>"))/SUMPRODUCT(ISNUMBER(TabelaServicos[Valor Previsto])*(TabelaServicos[Status]<>"Cancelado")*(TabelaServicos[Status]<>"Retirado do Escopo")*(TabelaServicos[Status]<>"Substituído")*(TabelaServicos[Peso Ajustado (manual)]=""))),$R6/SUMIFS($R:$R,$L:$L,"<>Cancelado",$L:$L,"<>Retirado do Escopo",$L:$L,"<>Substituído",$J:$J,"<>",$Q:$Q,"")*(1-SUMIFS($Q:$Q,$L:$L,"<>Cancelado",$L:$L,"<>Retirado do Escopo",$L:$L,"<>Substituído",$J:$J,"<>",$Q:$Q,"<>"))))) | T6: =IF(OR($S6="",$P6=""),"",$S6*$P6) | U6: =IF($C6="","",INDEX(Subetapas!$A:$A,MATCH($C6,Subetapas!$B:$B,0)))
A7: =IF($B7="","","SRV-"&TEXT(ROW()-1,"0000")) | G7: =IF(OR($E7="",$F7=""),"",$E7*$F7) | I7: =IF($H7="","NÃO","SIM") | J7: =IF($H7="",$G7,$H7) | K7: =IF(OR($J7="",$G7=""),"",$J7-$G7) | O7: =IF($A7="","",SUMIFS(Execução!$D:$D,Execução!$F:$F,$A7)) | P7: =IF($A7="","",IF($M7="Quantitativo",IF(OR($E7="",$E7=0),"",$O7/$E7),IF($M7="Status",IF($N7="Pendente",0,IF($N7="Em andamento",0.5,IF($N7="Concluído",1,""))),""))) | R7: =IF(OR($A7="",$L7="Cancelado",$L7="Retirado do Escopo",$L7="Substituído",$J7=""),"",IF(SUMIFS($J:$J,$L:$L,"<>Cancelado",$L:$L,"<>Retirado do Escopo",$L:$L,"<>Substituído",$J:$J,"<>")=0,"N/D",$J7/SUMIFS($J:$J,$L:$L,"<>Cancelado",$L:$L,"<>Retirado do Escopo",$L:$L,"<>Substituído",$J:$J,"<>"))) | S7: =IF(OR($A7="",$L7="Cancelado",$L7="Retirado do Escopo",$L7="Substituído",$J7=""),"",IF($Q7<>"",$Q7,IF(SUMIFS($R:$R,$L:$L,"<>Cancelado",$L:$L,"<>Retirado do Escopo",$L:$L,"<>Substituído",$J:$J,"<>",$Q:$Q,"")=0,IF(SUMPRODUCT(ISNUMBER(TabelaServicos[Valor Previsto])*(TabelaServicos[Status]<>"Cancelado")*(TabelaServicos[Status]<>"Retirado do Escopo")*(TabelaServicos[Status]<>"Substituído")*(TabelaServicos[Peso Ajustado (manual)]=""))=0,"N/D",(1-SUMIFS($Q:$Q,$L:$L,"<>Cancelado",$L:$L,"<>Retirado do Escopo",$L:$L,"<>Substituído",$J:$J,"<>",$Q:$Q,"<>"))/SUMPRODUCT(ISNUMBER(TabelaServicos[Valor Previsto])*(TabelaServicos[Status]<>"Cancelado")*(TabelaServicos[Status]<>"Retirado do Escopo")*(TabelaServicos[Status]<>"Substituído")*(TabelaServicos[Peso Ajustado (manual)]=""))),$R7/SUMIFS($R:$R,$L:$L,"<>Cancelado",$L:$L,"<>Retirado do Escopo",$L:$L,"<>Substituído",$J:$J,"<>",$Q:$Q,"")*(1-SUMIFS($Q:$Q,$L:$L,"<>Cancelado",$L:$L,"<>Retirado do Escopo",$L:$L,"<>Substituído",$J:$J,"<>",$Q:$Q,"<>"))))) | T7: =IF(OR($S7="",$P7=""),"",$S7*$P7) | U7: =IF($C7="","",INDEX(Subetapas!$A:$A,MATCH($C7,Subetapas!$B:$B,0)))
A8: =IF($B8="","","SRV-"&TEXT(ROW()-1,"0000")) | G8: =IF(OR($E8="",$F8=""),"",$E8*$F8) | I8: =IF($H8="","NÃO","SIM") | J8: =IF($H8="",$G8,$H8) | K8: =IF(OR($J8="",$G8=""),"",$J8-$G8) | O8: =IF($A8="","",SUMIFS(Execução!$D:$D,Execução!$F:$F,$A8)) | P8: =IF($A8="","",IF($M8="Quantitativo",IF(OR($E8="",$E8=0),"",$O8/$E8),IF($M8="Status",IF($N8="Pendente",0,IF($N8="Em andamento",0.5,IF($N8="Concluído",1,""))),""))) | R8: =IF(OR($A8="",$L8="Cancelado",$L8="Retirado do Escopo",$L8="Substituído",$J8=""),"",IF(SUMIFS($J:$J,$L:$L,"<>Cancelado",$L:$L,"<>Retirado do Escopo",$L:$L,"<>Substituído",$J:$J,"<>")=0,"N/D",$J8/SUMIFS($J:$J,$L:$L,"<>Cancelado",$L:$L,"<>Retirado do Escopo",$L:$L,"<>Substituído",$J:$J,"<>"))) | S8: =IF(OR($A8="",$L8="Cancelado",$L8="Retirado do Escopo",$L8="Substituído",$J8=""),"",IF($Q8<>"",$Q8,IF(SUMIFS($R:$R,$L:$L,"<>Cancelado",$L:$L,"<>Retirado do Escopo",$L:$L,"<>Substituído",$J:$J,"<>",$Q:$Q,"")=0,IF(SUMPRODUCT(ISNUMBER(TabelaServicos[Valor Previsto])*(TabelaServicos[Status]<>"Cancelado")*(TabelaServicos[Status]<>"Retirado do Escopo")*(TabelaServicos[Status]<>"Substituído")*(TabelaServicos[Peso Ajustado (manual)]=""))=0,"N/D",(1-SUMIFS($Q:$Q,$L:$L,"<>Cancelado",$L:$L,"<>Retirado do Escopo",$L:$L,"<>Substituído",$J:$J,"<>",$Q:$Q,"<>"))/SUMPRODUCT(ISNUMBER(TabelaServicos[Valor Previsto])*(TabelaServicos[Status]<>"Cancelado")*(TabelaServicos[Status]<>"Retirado do Escopo")*(TabelaServicos[Status]<>"Substituído")*(TabelaServicos[Peso Ajustado (manual)]=""))),$R8/SUMIFS($R:$R,$L:$L,"<>Cancelado",$L:$L,"<>Retirado do Escopo",$L:$L,"<>Substituído",$J:$J,"<>",$Q:$Q,"")*(1-SUMIFS($Q:$Q,$L:$L,"<>Cancelado",$L:$L,"<>Retirado do Escopo",$L:$L,"<>Substituído",$J:$J,"<>",$Q:$Q,"<>"))))) | T8: =IF(OR($S8="",$P8=""),"",$S8*$P8) | U8: =IF($C8="","",INDEX(Subetapas!$A:$A,MATCH($C8,Subetapas!$B:$B,0)))
A9: =IF($B9="","","SRV-"&TEXT(ROW()-1,"0000")) | G9: =IF(OR($E9="",$F9=""),"",$E9*$F9) | I9: =IF($H9="","NÃO","SIM") | J9: =IF($H9="",$G9,$H9) | K9: =IF(OR($J9="",$G9=""),"",$J9-$G9) | O9: =IF($A9="","",SUMIFS(Execução!$D:$D,Execução!$F:$F,$A9)) | P9: =IF($A9="","",IF($M9="Quantitativo",IF(OR($E9="",$E9=0),"",$O9/$E9),IF($M9="Status",IF($N9="Pendente",0,IF($N9="Em andamento",0.5,IF($N9="Concluído",1,""))),""))) | R9: =IF(OR($A9="",$L9="Cancelado",$L9="Retirado do Escopo",$L9="Substituído",$J9=""),"",IF(SUMIFS($J:$J,$L:$L,"<>Cancelado",$L:$L,"<>Retirado do Escopo",$L:$L,"<>Substituído",$J:$J,"<>")=0,"N/D",$J9/SUMIFS($J:$J,$L:$L,"<>Cancelado",$L:$L,"<>Retirado do Escopo",$L:$L,"<>Substituído",$J:$J,"<>"))) | S9: =IF(OR($A9="",$L9="Cancelado",$L9="Retirado do Escopo",$L9="Substituído",$J9=""),"",IF($Q9<>"",$Q9,IF(SUMIFS($R:$R,$L:$L,"<>Cancelado",$L:$L,"<>Retirado do Escopo",$L:$L,"<>Substituído",$J:$J,"<>",$Q:$Q,"")=0,IF(SUMPRODUCT(ISNUMBER(TabelaServicos[Valor Previsto])*(TabelaServicos[Status]<>"Cancelado")*(TabelaServicos[Status]<>"Retirado do Escopo")*(TabelaServicos[Status]<>"Substituído")*(TabelaServicos[Peso Ajustado (manual)]=""))=0,"N/D",(1-SUMIFS($Q:$Q,$L:$L,"<>Cancelado",$L:$L,"<>Retirado do Escopo",$L:$L,"<>Substituído",$J:$J,"<>",$Q:$Q,"<>"))/SUMPRODUCT(ISNUMBER(TabelaServicos[Valor Previsto])*(TabelaServicos[Status]<>"Cancelado")*(TabelaServicos[Status]<>"Retirado do Escopo")*(TabelaServicos[Status]<>"Substituído")*(TabelaServicos[Peso Ajustado (manual)]=""))),$R9/SUMIFS($R:$R,$L:$L,"<>Cancelado",$L:$L,"<>Retirado do Escopo",$L:$L,"<>Substituído",$J:$J,"<>",$Q:$Q,"")*(1-SUMIFS($Q:$Q,$L:$L,"<>Cancelado",$L:$L,"<>Retirado do Escopo",$L:$L,"<>Substituído",$J:$J,"<>",$Q:$Q,"<>"))))) | T9: =IF(OR($S9="",$P9=""),"",$S9*$P9) | U9: =IF($C9="","",INDEX(Subetapas!$A:$A,MATCH($C9,Subetapas!$B:$B,0)))
A10: =IF($B10="","","SRV-"&TEXT(ROW()-1,"0000")) | G10: =IF(OR($E10="",$F10=""),"",$E10*$F10) | I10: =IF($H10="","NÃO","SIM") | J10: =IF($H10="",$G10,$H10) | K10: =IF(OR($J10="",$G10=""),"",$J10-$G10) | O10: =IF($A10="","",SUMIFS(Execução!$D:$D,Execução!$F:$F,$A10)) | P10: =IF($A10="","",IF($M10="Quantitativo",IF(OR($E10="",$E10=0),"",$O10/$E10),IF($M10="Status",IF($N10="Pendente",0,IF($N10="Em andamento",0.5,IF($N10="Concluído",1,""))),""))) | R10: =IF(OR($A10="",$L10="Cancelado",$L10="Retirado do Escopo",$L10="Substituído",$J10=""),"",IF(SUMIFS($J:$J,$L:$L,"<>Cancelado",$L:$L,"<>Retirado do Escopo",$L:$L,"<>Substituído",$J:$J,"<>")=0,"N/D",$J10/SUMIFS($J:$J,$L:$L,"<>Cancelado",$L:$L,"<>Retirado do Escopo",$L:$L,"<>Substituído",$J:$J,"<>"))) | S10: =IF(OR($A10="",$L10="Cancelado",$L10="Retirado do Escopo",$L10="Substituído",$J10=""),"",IF($Q10<>"",$Q10,IF(SUMIFS($R:$R,$L:$L,"<>Cancelado",$L:$L,"<>Retirado do Escopo",$L:$L,"<>Substituído",$J:$J,"<>",$Q:$Q,"")=0,IF(SUMPRODUCT(ISNUMBER(TabelaServicos[Valor Previsto])*(TabelaServicos[Status]<>"Cancelado")*(TabelaServicos[Status]<>"Retirado do Escopo")*(TabelaServicos[Status]<>"Substituído")*(TabelaServicos[Peso Ajustado (manual)]=""))=0,"N/D",(1-SUMIFS($Q:$Q,$L:$L,"<>Cancelado",$L:$L,"<>Retirado do Escopo",$L:$L,"<>Substituído",$J:$J,"<>",$Q:$Q,"<>"))/SUMPRODUCT(ISNUMBER(TabelaServicos[Valor Previsto])*(TabelaServicos[Status]<>"Cancelado")*(TabelaServicos[Status]<>"Retirado do Escopo")*(TabelaServicos[Status]<>"Substituído")*(TabelaServicos[Peso Ajustado (manual)]=""))),$R10/SUMIFS($R:$R,$L:$L,"<>Cancelado",$L:$L,"<>Retirado do Escopo",$L:$L,"<>Substituído",$J:$J,"<>",$Q:$Q,"")*(1-SUMIFS($Q:$Q,$L:$L,"<>Cancelado",$L:$L,"<>Retirado do Escopo",$L:$L,"<>Substituído",$J:$J,"<>",$Q:$Q,"<>"))))) | T10: =IF(OR($S10="",$P10=""),"",$S10*$P10) | U10: =IF($C10="","",INDEX(Subetapas!$A:$A,MATCH($C10,Subetapas!$B:$B,0)))
A11: =IF($B11="","","SRV-"&TEXT(ROW()-1,"0000")) | G11: =IF(OR($E11="",$F11=""),"",$E11*$F11) | I11: =IF($H11="","NÃO","SIM") | J11: =IF($H11="",$G11,$H11) | K11: =IF(OR($J11="",$G11=""),"",$J11-$G11) | O11: =IF($A11="","",SUMIFS(Execução!$D:$D,Execução!$F:$F,$A11)) | P11: =IF($A11="","",IF($M11="Quantitativo",IF(OR($E11="",$E11=0),"",$O11/$E11),IF($M11="Status",IF($N11="Pendente",0,IF($N11="Em andamento",0.5,IF($N11="Concluído",1,""))),""))) | R11: =IF(OR($A11="",$L11="Cancelado",$L11="Retirado do Escopo",$L11="Substituído",$J11=""),"",IF(SUMIFS($J:$J,$L:$L,"<>Cancelado",$L:$L,"<>Retirado do Escopo",$L:$L,"<>Substituído",$J:$J,"<>")=0,"N/D",$J11/SUMIFS($J:$J,$L:$L,"<>Cancelado",$L:$L,"<>Retirado do Escopo",$L:$L,"<>Substituído",$J:$J,"<>"))) | S11: =IF(OR($A11="",$L11="Cancelado",$L11="Retirado do Escopo",$L11="Substituído",$J11=""),"",IF($Q11<>"",$Q11,IF(SUMIFS($R:$R,$L:$L,"<>Cancelado",$L:$L,"<>Retirado do Escopo",$L:$L,"<>Substituído",$J:$J,"<>",$Q:$Q,"")=0,IF(SUMPRODUCT(ISNUMBER(TabelaServicos[Valor Previsto])*(TabelaServicos[Status]<>"Cancelado")*(TabelaServicos[Status]<>"Retirado do Escopo")*(TabelaServicos[Status]<>"Substituído")*(TabelaServicos[Peso Ajustado (manual)]=""))=0,"N/D",(1-SUMIFS($Q:$Q,$L:$L,"<>Cancelado",$L:$L,"<>Retirado do Escopo",$L:$L,"<>Substituído",$J:$J,"<>",$Q:$Q,"<>"))/SUMPRODUCT(ISNUMBER(TabelaServicos[Valor Previsto])*(TabelaServicos[Status]<>"Cancelado")*(TabelaServicos[Status]<>"Retirado do Escopo")*(TabelaServicos[Status]<>"Substituído")*(TabelaServicos[Peso Ajustado (manual)]=""))),$R11/SUMIFS($R:$R,$L:$L,"<>Cancelado",$L:$L,"<>Retirado do Escopo",$L:$L,"<>Substituído",$J:$J,"<>",$Q:$Q,"")*(1-SUMIFS($Q:$Q,$L:$L,"<>Cancelado",$L:$L,"<>Retirado do Escopo",$L:$L,"<>Substituído",$J:$J,"<>",$Q:$Q,"<>"))))) | T11: =IF(OR($S11="",$P11=""),"",$S11*$P11) | U11: =IF($C11="","",INDEX(Subetapas!$A:$A,MATCH($C11,Subetapas!$B:$B,0)))
A12: =IF($B12="","","SRV-"&TEXT(ROW()-1,"0000")) | G12: =IF(OR($E12="",$F12=""),"",$E12*$F12) | I12: =IF($H12="","NÃO","SIM") | J12: =IF($H12="",$G12,$H12) | K12: =IF(OR($J12="",$G12=""),"",$J12-$G12) | O12: =IF($A12="","",SUMIFS(Execução!$D:$D,Execução!$F:$F,$A12)) | P12: =IF($A12="","",IF($M12="Quantitativo",IF(OR($E12="",$E12=0),"",$O12/$E12),IF($M12="Status",IF($N12="Pendente",0,IF($N12="Em andamento",0.5,IF($N12="Concluído",1,""))),""))) | R12: =IF(OR($A12="",$L12="Cancelado",$L12="Retirado do Escopo",$L12="Substituído",$J12=""),"",IF(SUMIFS($J:$J,$L:$L,"<>Cancelado",$L:$L,"<>Retirado do Escopo",$L:$L,"<>Substituído",$J:$J,"<>")=0,"N/D",$J12/SUMIFS($J:$J,$L:$L,"<>Cancelado",$L:$L,"<>Retirado do Escopo",$L:$L,"<>Substituído",$J:$J,"<>"))) | S12: =IF(OR($A12="",$L12="Cancelado",$L12="Retirado do Escopo",$L12="Substituído",$J12=""),"",IF($Q12<>"",$Q12,IF(SUMIFS($R:$R,$L:$L,"<>Cancelado",$L:$L,"<>Retirado do Escopo",$L:$L,"<>Substituído",$J:$J,"<>",$Q:$Q,"")=0,IF(SUMPRODUCT(ISNUMBER(TabelaServicos[Valor Previsto])*(TabelaServicos[Status]<>"Cancelado")*(TabelaServicos[Status]<>"Retirado do Escopo")*(TabelaServicos[Status]<>"Substituído")*(TabelaServicos[Peso Ajustado (manual)]=""))=0,"N/D",(1-SUMIFS($Q:$Q,$L:$L,"<>Cancelado",$L:$L,"<>Retirado do Escopo",$L:$L,"<>Substituído",$J:$J,"<>",$Q:$Q,"<>"))/SUMPRODUCT(ISNUMBER(TabelaServicos[Valor Previsto])*(TabelaServicos[Status]<>"Cancelado")*(TabelaServicos[Status]<>"Retirado do Escopo")*(TabelaServicos[Status]<>"Substituído")*(TabelaServicos[Peso Ajustado (manual)]=""))),$R12/SUMIFS($R:$R,$L:$L,"<>Cancelado",$L:$L,"<>Retirado do Escopo",$L:$L,"<>Substituído",$J:$J,"<>",$Q:$Q,"")*(1-SUMIFS($Q:$Q,$L:$L,"<>Cancelado",$L:$L,"<>Retirado do Escopo",$L:$L,"<>Substituído",$J:$J,"<>",$Q:$Q,"<>"))))) | T12: =IF(OR($S12="",$P12=""),"",$S12*$P12) | U12: =IF($C12="","",INDEX(Subetapas!$A:$A,MATCH($C12,Subetapas!$B:$B,0)))
A13: =IF($B13="","","SRV-"&TEXT(ROW()-1,"0000")) | G13: =IF(OR($E13="",$F13=""),"",$E13*$F13) | I13: =IF($H13="","NÃO","SIM") | J13: =IF($H13="",$G13,$H13) | K13: =IF(OR($J13="",$G13=""),"",$J13-$G13) | O13: =IF($A13="","",SUMIFS(Execução!$D:$D,Execução!$F:$F,$A13)) | P13: =IF($A13="","",IF($M13="Quantitativo",IF(OR($E13="",$E13=0),"",$O13/$E13),IF($M13="Status",IF($N13="Pendente",0,IF($N13="Em andamento",0.5,IF($N13="Concluído",1,""))),""))) | R13: =IF(OR($A13="",$L13="Cancelado",$L13="Retirado do Escopo",$L13="Substituído",$J13=""),"",IF(SUMIFS($J:$J,$L:$L,"<>Cancelado",$L:$L,"<>Retirado do Escopo",$L:$L,"<>Substituído",$J:$J,"<>")=0,"N/D",$J13/SUMIFS($J:$J,$L:$L,"<>Cancelado",$L:$L,"<>Retirado do Escopo",$L:$L,"<>Substituído",$J:$J,"<>"))) | S13: =IF(OR($A13="",$L13="Cancelado",$L13="Retirado do Escopo",$L13="Substituído",$J13=""),"",IF($Q13<>"",$Q13,IF(SUMIFS($R:$R,$L:$L,"<>Cancelado",$L:$L,"<>Retirado do Escopo",$L:$L,"<>Substituído",$J:$J,"<>",$Q:$Q,"")=0,IF(SUMPRODUCT(ISNUMBER(TabelaServicos[Valor Previsto])*(TabelaServicos[Status]<>"Cancelado")*(TabelaServicos[Status]<>"Retirado do Escopo")*(TabelaServicos[Status]<>"Substituído")*(TabelaServicos[Peso Ajustado (manual)]=""))=0,"N/D",(1-SUMIFS($Q:$Q,$L:$L,"<>Cancelado",$L:$L,"<>Retirado do Escopo",$L:$L,"<>Substituído",$J:$J,"<>",$Q:$Q,"<>"))/SUMPRODUCT(ISNUMBER(TabelaServicos[Valor Previsto])*(TabelaServicos[Status]<>"Cancelado")*(TabelaServicos[Status]<>"Retirado do Escopo")*(TabelaServicos[Status]<>"Substituído")*(TabelaServicos[Peso Ajustado (manual)]=""))),$R13/SUMIFS($R:$R,$L:$L,"<>Cancelado",$L:$L,"<>Retirado do Escopo",$L:$L,"<>Substituído",$J:$J,"<>",$Q:$Q,"")*(1-SUMIFS($Q:$Q,$L:$L,"<>Cancelado",$L:$L,"<>Retirado do Escopo",$L:$L,"<>Substituído",$J:$J,"<>",$Q:$Q,"<>"))))) | T13: =IF(OR($S13="",$P13=""),"",$S13*$P13) | U13: =IF($C13="","",INDEX(Subetapas!$A:$A,MATCH($C13,Subetapas!$B:$B,0)))
... A31: =IF($B31="","","SRV-"&TEXT(ROW()-1,"0000")) | G31: =IF(OR($E31="",$F31=""),"",$E31*$F31) | I31: =IF($H31="","NÃO","SIM") | J31: =IF($H31="",$G31,$H31) | K31: =IF(OR($J31="",$G31=""),"",$J31-$G31) | O31: =IF($A31="","",SUMIFS(Execução!$D:$D,Execução!$F:$F,$A31)) | P31: =IF($A31="","",IF($M31="Quantitativo",IF(OR($E31="",$E31=0),"",$O31/$E31),IF($M31="Status",IF($N31="Pendente",0,IF($N31="Em andamento",0.5,IF($N31="Concluído",1,""))),""))) | R31: =IF(OR($A31="",$L31="Cancelado",$L31="Retirado do Escopo",$L31="Substituído",$J31=""),"",IF(SUMIFS($J:$J,$L:$L,"<>Cancelado",$L:$L,"<>Retirado do Escopo",$L:$L,"<>Substituído",$J:$J,"<>")=0,"N/D",$J31/SUMIFS($J:$J,$L:$L,"<>Cancelado",$L:$L,"<>Retirado do Escopo",$L:$L,"<>Substituído",$J:$J,"<>"))) | S31: =IF(OR($A31="",$L31="Cancelado",$L31="Retirado do Escopo",$L31="Substituído",$J31=""),"",IF($Q31<>"",$Q31,IF(SUMIFS($R:$R,$L:$L,"<>Cancelado",$L:$L,"<>Retirado do Escopo",$L:$L,"<>Substituído",$J:$J,"<>",$Q:$Q,"")=0,IF(SUMPRODUCT(ISNUMBER(TabelaServicos[Valor Previsto])*(TabelaServicos[Status]<>"Cancelado")*(TabelaServicos[Status]<>"Retirado do Escopo")*(TabelaServicos[Status]<>"Substituído")*(TabelaServicos[Peso Ajustado (manual)]=""))=0,"N/D",(1-SUMIFS($Q:$Q,$L:$L,"<>Cancelado",$L:$L,"<>Retirado do Escopo",$L:$L,"<>Substituído",$J:$J,"<>",$Q:$Q,"<>"))/SUMPRODUCT(ISNUMBER(TabelaServicos[Valor Previsto])*(TabelaServicos[Status]<>"Cancelado")*(TabelaServicos[Status]<>"Retirado do Escopo")*(TabelaServicos[Status]<>"Substituído")*(TabelaServicos[Peso Ajustado (manual)]=""))),$R31/SUMIFS($R:$R,$L:$L,"<>Cancelado",$L:$L,"<>Retirado do Escopo",$L:$L,"<>Substituído",$J:$J,"<>",$Q:$Q,"")*(1-SUMIFS($Q:$Q,$L:$L,"<>Cancelado",$L:$L,"<>Retirado do Escopo",$L:$L,"<>Substituído",$J:$J,"<>",$Q:$Q,"<>"))))) | T31: =IF(OR($S31="",$P31=""),"",$S31*$P31) | U31: =IF($C31="","",INDEX(Subetapas!$A:$A,MATCH($C31,Subetapas!$B:$B,0)))

Sheet Execução
A1: ID (técnico) | B1: Serviço | C1: Data da Medição | D1: Quantidade Executada | E1: Responsável | F1: ID_Servico (técnico)
A2: =IF($B2="","","EXE-"&TEXT(ROW()-1,"0000")) | F2: =IF($B2="","",INDEX(Serviços!$A:$A,MATCH($B2,Serviços!$B:$B,0)))
A3: =IF($B3="","","EXE-"&TEXT(ROW()-1,"0000")) | F3: =IF($B3="","",INDEX(Serviços!$A:$A,MATCH($B3,Serviços!$B:$B,0)))
A4: =IF($B4="","","EXE-"&TEXT(ROW()-1,"0000")) | F4: =IF($B4="","",INDEX(Serviços!$A:$A,MATCH($B4,Serviços!$B:$B,0)))
A5: =IF($B5="","","EXE-"&TEXT(ROW()-1,"0000")) | F5: =IF($B5="","",INDEX(Serviços!$A:$A,MATCH($B5,Serviços!$B:$B,0)))
A6: =IF($B6="","","EXE-"&TEXT(ROW()-1,"0000")) | F6: =IF($B6="","",INDEX(Serviços!$A:$A,MATCH($B6,Serviços!$B:$B,0)))
A7: =IF($B7="","","EXE-"&TEXT(ROW()-1,"0000")) | F7: =IF($B7="","",INDEX(Serviços!$A:$A,MATCH($B7,Serviços!$B:$B,0)))
A8: =IF($B8="","","EXE-"&TEXT(ROW()-1,"0000")) | F8: =IF($B8="","",INDEX(Serviços!$A:$A,MATCH($B8,Serviços!$B:$B,0)))
A9: =IF($B9="","","EXE-"&TEXT(ROW()-1,"0000")) | F9: =IF($B9="","",INDEX(Serviços!$A:$A,MATCH($B9,Serviços!$B:$B,0)))
A10: =IF($B10="","","EXE-"&TEXT(ROW()-1,"0000")) | F10: =IF($B10="","",INDEX(Serviços!$A:$A,MATCH($B10,Serviços!$B:$B,0)))
A11: =IF($B11="","","EXE-"&TEXT(ROW()-1,"0000")) | F11: =IF($B11="","",INDEX(Serviços!$A:$A,MATCH($B11,Serviços!$B:$B,0)))
A12: =IF($B12="","","EXE-"&TEXT(ROW()-1,"0000")) | F12: =IF($B12="","",INDEX(Serviços!$A:$A,MATCH($B12,Serviços!$B:$B,0)))
A13: =IF($B13="","","EXE-"&TEXT(ROW()-1,"0000")) | F13: =IF($B13="","",INDEX(Serviços!$A:$A,MATCH($B13,Serviços!$B:$B,0)))
... A31: =IF($B31="","","EXE-"&TEXT(ROW()-1,"0000")) | F31: =IF($B31="","",INDEX(Serviços!$A:$A,MATCH($B31,Serviços!$B:$B,0)))

Sheet Financeiro
A1: ID (técnico) | B1: Tipo | C1: Data | D1: Descrição | E1: Valor | F1: Entrada/Saída | G1: Aporte | H1: Custo Realizado | I1: Total Pago | J1: A Pagar | K1: Situação | L1: Observação | M1: ID_Obra (técnico)
A2: =IF($B2="","","FIN-"&TEXT(ROW()-1,"0000")) | F2: =IF($B2="","",IF($B2="Aporte","Entrada",IF($B2="Outras Entradas","Entrada",IF($B2="Outras Saídas","Saída","Custo (Caixa só no Pagamento)")))) | G2: =IF($B2="Aporte",$E2,"") | H2: =IF($B2="Despesa/Custo",$E2,"") | I2: =IF($B2="Despesa/Custo",SUMIFS(Pagamentos!$D:$D,Pagamentos!$F:$F,$A2),"") | J2: =IF($B2="Despesa/Custo",$H2-$I2,"") | M2: =IF($B2="","",Base_Dados!$B$2)
A3: =IF($B3="","","FIN-"&TEXT(ROW()-1,"0000")) | F3: =IF($B3="","",IF($B3="Aporte","Entrada",IF($B3="Outras Entradas","Entrada",IF($B3="Outras Saídas","Saída","Custo (Caixa só no Pagamento)")))) | G3: =IF($B3="Aporte",$E3,"") | H3: =IF($B3="Despesa/Custo",$E3,"") | I3: =IF($B3="Despesa/Custo",SUMIFS(Pagamentos!$D:$D,Pagamentos!$F:$F,$A3),"") | J3: =IF($B3="Despesa/Custo",$H3-$I3,"") | M3: =IF($B3="","",Base_Dados!$B$2)
A4: =IF($B4="","","FIN-"&TEXT(ROW()-1,"0000")) | F4: =IF($B4="","",IF($B4="Aporte","Entrada",IF($B4="Outras Entradas","Entrada",IF($B4="Outras Saídas","Saída","Custo (Caixa só no Pagamento)")))) | G4: =IF($B4="Aporte",$E4,"") | H4: =IF($B4="Despesa/Custo",$E4,"") | I4: =IF($B4="Despesa/Custo",SUMIFS(Pagamentos!$D:$D,Pagamentos!$F:$F,$A4),"") | J4: =IF($B4="Despesa/Custo",$H4-$I4,"") | M4: =IF($B4="","",Base_Dados!$B$2)
A5: =IF($B5="","","FIN-"&TEXT(ROW()-1,"0000")) | F5: =IF($B5="","",IF($B5="Aporte","Entrada",IF($B5="Outras Entradas","Entrada",IF($B5="Outras Saídas","Saída","Custo (Caixa só no Pagamento)")))) | G5: =IF($B5="Aporte",$E5,"") | H5: =IF($B5="Despesa/Custo",$E5,"") | I5: =IF($B5="Despesa/Custo",SUMIFS(Pagamentos!$D:$D,Pagamentos!$F:$F,$A5),"") | J5: =IF($B5="Despesa/Custo",$H5-$I5,"") | M5: =IF($B5="","",Base_Dados!$B$2)
A6: =IF($B6="","","FIN-"&TEXT(ROW()-1,"0000")) | F6: =IF($B6="","",IF($B6="Aporte","Entrada",IF($B6="Outras Entradas","Entrada",IF($B6="Outras Saídas","Saída","Custo (Caixa só no Pagamento)")))) | G6: =IF($B6="Aporte",$E6,"") | H6: =IF($B6="Despesa/Custo",$E6,"") | I6: =IF($B6="Despesa/Custo",SUMIFS(Pagamentos!$D:$D,Pagamentos!$F:$F,$A6),"") | J6: =IF($B6="Despesa/Custo",$H6-$I6,"") | M6: =IF($B6="","",Base_Dados!$B$2)
A7: =IF($B7="","","FIN-"&TEXT(ROW()-1,"0000")) | F7: =IF($B7="","",IF($B7="Aporte","Entrada",IF($B7="Outras Entradas","Entrada",IF($B7="Outras Saídas","Saída","Custo (Caixa só no Pagamento)")))) | G7: =IF($B7="Aporte",$E7,"") | H7: =IF($B7="Despesa/Custo",$E7,"") | I7: =IF($B7="Despesa/Custo",SUMIFS(Pagamentos!$D:$D,Pagamentos!$F:$F,$A7),"") | J7: =IF($B7="Despesa/Custo",$H7-$I7,"") | M7: =IF($B7="","",Base_Dados!$B$2)
A8: =IF($B8="","","FIN-"&TEXT(ROW()-1,"0000")) | F8: =IF($B8="","",IF($B8="Aporte","Entrada",IF($B8="Outras Entradas","Entrada",IF($B8="Outras Saídas","Saída","Custo (Caixa só no Pagamento)")))) | G8: =IF($B8="Aporte",$E8,"") | H8: =IF($B8="Despesa/Custo",$E8,"") | I8: =IF($B8="Despesa/Custo",SUMIFS(Pagamentos!$D:$D,Pagamentos!$F:$F,$A8),"") | J8: =IF($B8="Despesa/Custo",$H8-$I8,"") | M8: =IF($B8="","",Base_Dados!$B$2)
A9: =IF($B9="","","FIN-"&TEXT(ROW()-1,"0000")) | F9: =IF($B9="","",IF($B9="Aporte","Entrada",IF($B9="Outras Entradas","Entrada",IF($B9="Outras Saídas","Saída","Custo (Caixa só no Pagamento)")))) | G9: =IF($B9="Aporte",$E9,"") | H9: =IF($B9="Despesa/Custo",$E9,"") | I9: =IF($B9="Despesa/Custo",SUMIFS(Pagamentos!$D:$D,Pagamentos!$F:$F,$A9),"") | J9: =IF($B9="Despesa/Custo",$H9-$I9,"") | M9: =IF($B9="","",Base_Dados!$B$2)
A10: =IF($B10="","","FIN-"&TEXT(ROW()-1,"0000")) | F10: =IF($B10="","",IF($B10="Aporte","Entrada",IF($B10="Outras Entradas","Entrada",IF($B10="Outras Saídas","Saída","Custo (Caixa só no Pagamento)")))) | G10: =IF($B10="Aporte",$E10,"") | H10: =IF($B10="Despesa/Custo",$E10,"") | I10: =IF($B10="Despesa/Custo",SUMIFS(Pagamentos!$D:$D,Pagamentos!$F:$F,$A10),"") | J10: =IF($B10="Despesa/Custo",$H10-$I10,"") | M10: =IF($B10="","",Base_Dados!$B$2)
A11: =IF($B11="","","FIN-"&TEXT(ROW()-1,"0000")) | F11: =IF($B11="","",IF($B11="Aporte","Entrada",IF($B11="Outras Entradas","Entrada",IF($B11="Outras Saídas","Saída","Custo (Caixa só no Pagamento)")))) | G11: =IF($B11="Aporte",$E11,"") | H11: =IF($B11="Despesa/Custo",$E11,"") | I11: =IF($B11="Despesa/Custo",SUMIFS(Pagamentos!$D:$D,Pagamentos!$F:$F,$A11),"") | J11: =IF($B11="Despesa/Custo",$H11-$I11,"") | M11: =IF($B11="","",Base_Dados!$B$2)
A12: =IF($B12="","","FIN-"&TEXT(ROW()-1,"0000")) | F12: =IF($B12="","",IF($B12="Aporte","Entrada",IF($B12="Outras Entradas","Entrada",IF($B12="Outras Saídas","Saída","Custo (Caixa só no Pagamento)")))) | G12: =IF($B12="Aporte",$E12,"") | H12: =IF($B12="Despesa/Custo",$E12,"") | I12: =IF($B12="Despesa/Custo",SUMIFS(Pagamentos!$D:$D,Pagamentos!$F:$F,$A12),"") | J12: =IF($B12="Despesa/Custo",$H12-$I12,"") | M12: =IF($B12="","",Base_Dados!$B$2)
A13: =IF($B13="","","FIN-"&TEXT(ROW()-1,"0000")) | F13: =IF($B13="","",IF($B13="Aporte","Entrada",IF($B13="Outras Entradas","Entrada",IF($B13="Outras Saídas","Saída","Custo (Caixa só no Pagamento)")))) | G13: =IF($B13="Aporte",$E13,"") | H13: =IF($B13="Despesa/Custo",$E13,"") | I13: =IF($B13="Despesa/Custo",SUMIFS(Pagamentos!$D:$D,Pagamentos!$F:$F,$A13),"") | J13: =IF($B13="Despesa/Custo",$H13-$I13,"") | M13: =IF($B13="","",Base_Dados!$B$2)
... A31: =IF($B31="","","FIN-"&TEXT(ROW()-1,"0000")) | F31: =IF($B31="","",IF($B31="Aporte","Entrada",IF($B31="Outras Entradas","Entrada",IF($B31="Outras Saídas","Saída","Custo (Caixa só no Pagamento)")))) | G31: =IF($B31="Aporte",$E31,"") | H31: =IF($B31="Despesa/Custo",$E31,"") | I31: =IF($B31="Despesa/Custo",SUMIFS(Pagamentos!$D:$D,Pagamentos!$F:$F,$A31),"") | J31: =IF($B31="Despesa/Custo",$H31-$I31,"") | M31: =IF($B31="","",Base_Dados!$B$2)

Sheet Pagamentos
A1: ID (técnico) | B1: Lançamento (Despesa/Custo) | C1: Data do Pagamento | D1: Valor Pago | E1: Observação | F1: ID_Financeiro (técnico)
A2: =IF($B2="","","PGT-"&TEXT(ROW()-1,"0000")) | F2: =IF($B2="","",INDEX(Financeiro!$A:$A,MATCH($B2,Financeiro!$D:$D,0)))
A3: =IF($B3="","","PGT-"&TEXT(ROW()-1,"0000")) | F3: =IF($B3="","",INDEX(Financeiro!$A:$A,MATCH($B3,Financeiro!$D:$D,0)))
A4: =IF($B4="","","PGT-"&TEXT(ROW()-1,"0000")) | F4: =IF($B4="","",INDEX(Financeiro!$A:$A,MATCH($B4,Financeiro!$D:$D,0)))
A5: =IF($B5="","","PGT-"&TEXT(ROW()-1,"0000")) | F5: =IF($B5="","",INDEX(Financeiro!$A:$A,MATCH($B5,Financeiro!$D:$D,0)))
A6: =IF($B6="","","PGT-"&TEXT(ROW()-1,"0000")) | F6: =IF($B6="","",INDEX(Financeiro!$A:$A,MATCH($B6,Financeiro!$D:$D,0)))
A7: =IF($B7="","","PGT-"&TEXT(ROW()-1,"0000")) | F7: =IF($B7="","",INDEX(Financeiro!$A:$A,MATCH($B7,Financeiro!$D:$D,0)))
A8: =IF($B8="","","PGT-"&TEXT(ROW()-1,"0000")) | F8: =IF($B8="","",INDEX(Financeiro!$A:$A,MATCH($B8,Financeiro!$D:$D,0)))
A9: =IF($B9="","","PGT-"&TEXT(ROW()-1,"0000")) | F9: =IF($B9="","",INDEX(Financeiro!$A:$A,MATCH($B9,Financeiro!$D:$D,0)))
A10: =IF($B10="","","PGT-"&TEXT(ROW()-1,"0000")) | F10: =IF($B10="","",INDEX(Financeiro!$A:$A,MATCH($B10,Financeiro!$D:$D,0)))
A11: =IF($B11="","","PGT-"&TEXT(ROW()-1,"0000")) | F11: =IF($B11="","",INDEX(Financeiro!$A:$A,MATCH($B11,Financeiro!$D:$D,0)))
A12: =IF($B12="","","PGT-"&TEXT(ROW()-1,"0000")) | F12: =IF($B12="","",INDEX(Financeiro!$A:$A,MATCH($B12,Financeiro!$D:$D,0)))
A13: =IF($B13="","","PGT-"&TEXT(ROW()-1,"0000")) | F13: =IF($B13="","",INDEX(Financeiro!$A:$A,MATCH($B13,Financeiro!$D:$D,0)))
... A31: =IF($B31="","","PGT-"&TEXT(ROW()-1,"0000")) | F31: =IF($B31="","",INDEX(Financeiro!$A:$A,MATCH($B31,Financeiro!$D:$D,0)))

Sheet Alterações
A1: ID (técnico) | B1: Tipo | C1: Data | D1: Descrição | E1: Impacto no Orçamento | F1: Impacto no Prazo (dias) | G1: Status de Aprovação | H1: Solicitante | I1: ID_Obra (técnico)
A2: =IF($D2="","","ALT-"&TEXT(ROW()-1,"0000")) | I2: =IF($D2="","",Base_Dados!$B$2)
A3: =IF($D3="","","ALT-"&TEXT(ROW()-1,"0000")) | I3: =IF($D3="","",Base_Dados!$B$2)
A4: =IF($D4="","","ALT-"&TEXT(ROW()-1,"0000")) | I4: =IF($D4="","",Base_Dados!$B$2)
A5: =IF($D5="","","ALT-"&TEXT(ROW()-1,"0000")) | I5: =IF($D5="","",Base_Dados!$B$2)
A6: =IF($D6="","","ALT-"&TEXT(ROW()-1,"0000")) | I6: =IF($D6="","",Base_Dados!$B$2)
A7: =IF($D7="","","ALT-"&TEXT(ROW()-1,"0000")) | I7: =IF($D7="","",Base_Dados!$B$2)
A8: =IF($D8="","","ALT-"&TEXT(ROW()-1,"0000")) | I8: =IF($D8="","",Base_Dados!$B$2)
A9: =IF($D9="","","ALT-"&TEXT(ROW()-1,"0000")) | I9: =IF($D9="","",Base_Dados!$B$2)
A10: =IF($D10="","","ALT-"&TEXT(ROW()-1,"0000")) | I10: =IF($D10="","",Base_Dados!$B$2)
A11: =IF($D11="","","ALT-"&TEXT(ROW()-1,"0000")) | I11: =IF($D11="","",Base_Dados!$B$2)
A12: =IF($D12="","","ALT-"&TEXT(ROW()-1,"0000")) | I12: =IF($D12="","",Base_Dados!$B$2)
A13: =IF($D13="","","ALT-"&TEXT(ROW()-1,"0000")) | I13: =IF($D13="","",Base_Dados!$B$2)
... A31: =IF($D31="","","ALT-"&TEXT(ROW()-1,"0000")) | I31: =IF($D31="","",Base_Dados!$B$2)

Sheet Compras
A1: ID (técnico) | B1: Descrição | C1: Fornecedor | D1: Data da Compra | E1: Valor | F1: Forma de Pagamento | G1: Status de Aprovação | H1: Status de Entrega | I1: Etapa (opcional) | J1: Subetapa (opcional) | K1: Serviço (opcional) | L1: Planejado (Valor Previsto) | M1: Variação R$ | N1: Variação % | O1: Observação | P1: ID_Obra (técnico) | Q1: ID_Etapa (técnico) | R1: ID_Subetapa (técnico) | S1: ID_Servico (técnico)
A2: =IF($B2="","","COM-"&TEXT(ROW()-1,"0000")) | L2: =IF($S2="","",INDEX(Serviços!$J:$J,MATCH($S2,Serviços!$A:$A,0))) | M2: =IF(OR($L2="",$E2=""),"",$E2-$L2) | N2: =IF(OR($L2="",$E2=""),"",IF($L2=0,"N/D",$M2/$L2)) | P2: =IF($B2="","",Base_Dados!$B$2) | Q2: =IF($I2="","",INDEX(Etapas!$A:$A,MATCH($I2,Etapas!$B:$B,0))) | R2: =IF($J2="","",INDEX(Subetapas!$A:$A,MATCH($J2,Subetapas!$B:$B,0))) | S2: =IF($K2="","",INDEX(Serviços!$A:$A,MATCH($K2,Serviços!$B:$B,0)))
A3: =IF($B3="","","COM-"&TEXT(ROW()-1,"0000")) | L3: =IF($S3="","",INDEX(Serviços!$J:$J,MATCH($S3,Serviços!$A:$A,0))) | M3: =IF(OR($L3="",$E3=""),"",$E3-$L3) | N3: =IF(OR($L3="",$E3=""),"",IF($L3=0,"N/D",$M3/$L3)) | P3: =IF($B3="","",Base_Dados!$B$2) | Q3: =IF($I3="","",INDEX(Etapas!$A:$A,MATCH($I3,Etapas!$B:$B,0))) | R3: =IF($J3="","",INDEX(Subetapas!$A:$A,MATCH($J3,Subetapas!$B:$B,0))) | S3: =IF($K3="","",INDEX(Serviços!$A:$A,MATCH($K3,Serviços!$B:$B,0)))
A4: =IF($B4="","","COM-"&TEXT(ROW()-1,"0000")) | L4: =IF($S4="","",INDEX(Serviços!$J:$J,MATCH($S4,Serviços!$A:$A,0))) | M4: =IF(OR($L4="",$E4=""),"",$E4-$L4) | N4: =IF(OR($L4="",$E4=""),"",IF($L4=0,"N/D",$M4/$L4)) | P4: =IF($B4="","",Base_Dados!$B$2) | Q4: =IF($I4="","",INDEX(Etapas!$A:$A,MATCH($I4,Etapas!$B:$B,0))) | R4: =IF($J4="","",INDEX(Subetapas!$A:$A,MATCH($J4,Subetapas!$B:$B,0))) | S4: =IF($K4="","",INDEX(Serviços!$A:$A,MATCH($K4,Serviços!$B:$B,0)))
A5: =IF($B5="","","COM-"&TEXT(ROW()-1,"0000")) | L5: =IF($S5="","",INDEX(Serviços!$J:$J,MATCH($S5,Serviços!$A:$A,0))) | M5: =IF(OR($L5="",$E5=""),"",$E5-$L5) | N5: =IF(OR($L5="",$E5=""),"",IF($L5=0,"N/D",$M5/$L5)) | P5: =IF($B5="","",Base_Dados!$B$2) | Q5: =IF($I5="","",INDEX(Etapas!$A:$A,MATCH($I5,Etapas!$B:$B,0))) | R5: =IF($J5="","",INDEX(Subetapas!$A:$A,MATCH($J5,Subetapas!$B:$B,0))) | S5: =IF($K5="","",INDEX(Serviços!$A:$A,MATCH($K5,Serviços!$B:$B,0)))
A6: =IF($B6="","","COM-"&TEXT(ROW()-1,"0000")) | L6: =IF($S6="","",INDEX(Serviços!$J:$J,MATCH($S6,Serviços!$A:$A,0))) | M6: =IF(OR($L6="",$E6=""),"",$E6-$L6) | N6: =IF(OR($L6="",$E6=""),"",IF($L6=0,"N/D",$M6/$L6)) | P6: =IF($B6="","",Base_Dados!$B$2) | Q6: =IF($I6="","",INDEX(Etapas!$A:$A,MATCH($I6,Etapas!$B:$B,0))) | R6: =IF($J6="","",INDEX(Subetapas!$A:$A,MATCH($J6,Subetapas!$B:$B,0))) | S6: =IF($K6="","",INDEX(Serviços!$A:$A,MATCH($K6,Serviços!$B:$B,0)))
A7: =IF($B7="","","COM-"&TEXT(ROW()-1,"0000")) | L7: =IF($S7="","",INDEX(Serviços!$J:$J,MATCH($S7,Serviços!$A:$A,0))) | M7: =IF(OR($L7="",$E7=""),"",$E7-$L7) | N7: =IF(OR($L7="",$E7=""),"",IF($L7=0,"N/D",$M7/$L7)) | P7: =IF($B7="","",Base_Dados!$B$2) | Q7: =IF($I7="","",INDEX(Etapas!$A:$A,MATCH($I7,Etapas!$B:$B,0))) | R7: =IF($J7="","",INDEX(Subetapas!$A:$A,MATCH($J7,Subetapas!$B:$B,0))) | S7: =IF($K7="","",INDEX(Serviços!$A:$A,MATCH($K7,Serviços!$B:$B,0)))
A8: =IF($B8="","","COM-"&TEXT(ROW()-1,"0000")) | L8: =IF($S8="","",INDEX(Serviços!$J:$J,MATCH($S8,Serviços!$A:$A,0))) | M8: =IF(OR($L8="",$E8=""),"",$E8-$L8) | N8: =IF(OR($L8="",$E8=""),"",IF($L8=0,"N/D",$M8/$L8)) | P8: =IF($B8="","",Base_Dados!$B$2) | Q8: =IF($I8="","",INDEX(Etapas!$A:$A,MATCH($I8,Etapas!$B:$B,0))) | R8: =IF($J8="","",INDEX(Subetapas!$A:$A,MATCH($J8,Subetapas!$B:$B,0))) | S8: =IF($K8="","",INDEX(Serviços!$A:$A,MATCH($K8,Serviços!$B:$B,0)))
A9: =IF($B9="","","COM-"&TEXT(ROW()-1,"0000")) | L9: =IF($S9="","",INDEX(Serviços!$J:$J,MATCH($S9,Serviços!$A:$A,0))) | M9: =IF(OR($L9="",$E9=""),"",$E9-$L9) | N9: =IF(OR($L9="",$E9=""),"",IF($L9=0,"N/D",$M9/$L9)) | P9: =IF($B9="","",Base_Dados!$B$2) | Q9: =IF($I9="","",INDEX(Etapas!$A:$A,MATCH($I9,Etapas!$B:$B,0))) | R9: =IF($J9="","",INDEX(Subetapas!$A:$A,MATCH($J9,Subetapas!$B:$B,0))) | S9: =IF($K9="","",INDEX(Serviços!$A:$A,MATCH($K9,Serviços!$B:$B,0)))
A10: =IF($B10="","","COM-"&TEXT(ROW()-1,"0000")) | L10: =IF($S10="","",INDEX(Serviços!$J:$J,MATCH($S10,Serviços!$A:$A,0))) | M10: =IF(OR($L10="",$E10=""),"",$E10-$L10) | N10: =IF(OR($L10="",$E10=""),"",IF($L10=0,"N/D",$M10/$L10)) | P10: =IF($B10="","",Base_Dados!$B$2) | Q10: =IF($I10="","",INDEX(Etapas!$A:$A,MATCH($I10,Etapas!$B:$B,0))) | R10: =IF($J10="","",INDEX(Subetapas!$A:$A,MATCH($J10,Subetapas!$B:$B,0))) | S10: =IF($K10="","",INDEX(Serviços!$A:$A,MATCH($K10,Serviços!$B:$B,0)))
A11: =IF($B11="","","COM-"&TEXT(ROW()-1,"0000")) | L11: =IF($S11="","",INDEX(Serviços!$J:$J,MATCH($S11,Serviços!$A:$A,0))) | M11: =IF(OR($L11="",$E11=""),"",$E11-$L11) | N11: =IF(OR($L11="",$E11=""),"",IF($L11=0,"N/D",$M11/$L11)) | P11: =IF($B11="","",Base_Dados!$B$2) | Q11: =IF($I11="","",INDEX(Etapas!$A:$A,MATCH($I11,Etapas!$B:$B,0))) | R11: =IF($J11="","",INDEX(Subetapas!$A:$A,MATCH($J11,Subetapas!$B:$B,0))) | S11: =IF($K11="","",INDEX(Serviços!$A:$A,MATCH($K11,Serviços!$B:$B,0)))
A12: =IF($B12="","","COM-"&TEXT(ROW()-1,"0000")) | L12: =IF($S12="","",INDEX(Serviços!$J:$J,MATCH($S12,Serviços!$A:$A,0))) | M12: =IF(OR($L12="",$E12=""),"",$E12-$L12) | N12: =IF(OR($L12="",$E12=""),"",IF($L12=0,"N/D",$M12/$L12)) | P12: =IF($B12="","",Base_Dados!$B$2) | Q12: =IF($I12="","",INDEX(Etapas!$A:$A,MATCH($I12,Etapas!$B:$B,0))) | R12: =IF($J12="","",INDEX(Subetapas!$A:$A,MATCH($J12,Subetapas!$B:$B,0))) | S12: =IF($K12="","",INDEX(Serviços!$A:$A,MATCH($K12,Serviços!$B:$B,0)))
A13: =IF($B13="","","COM-"&TEXT(ROW()-1,"0000")) | L13: =IF($S13="","",INDEX(Serviços!$J:$J,MATCH($S13,Serviços!$A:$A,0))) | M13: =IF(OR($L13="",$E13=""),"",$E13-$L13) | N13: =IF(OR($L13="",$E13=""),"",IF($L13=0,"N/D",$M13/$L13)) | P13: =IF($B13="","",Base_Dados!$B$2) | Q13: =IF($I13="","",INDEX(Etapas!$A:$A,MATCH($I13,Etapas!$B:$B,0))) | R13: =IF($J13="","",INDEX(Subetapas!$A:$A,MATCH($J13,Subetapas!$B:$B,0))) | S13: =IF($K13="","",INDEX(Serviços!$A:$A,MATCH($K13,Serviços!$B:$B,0)))
... A31: =IF($B31="","","COM-"&TEXT(ROW()-1,"0000")) | L31: =IF($S31="","",INDEX(Serviços!$J:$J,MATCH($S31,Serviços!$A:$A,0))) | M31: =IF(OR($L31="",$E31=""),"",$E31-$L31) | N31: =IF(OR($L31="",$E31=""),"",IF($L31=0,"N/D",$M31/$L31)) | P31: =IF($B31="","",Base_Dados!$B$2) | Q31: =IF($I31="","",INDEX(Etapas!$A:$A,MATCH($I31,Etapas!$B:$B,0))) | R31: =IF($J31="","",INDEX(Subetapas!$A:$A,MATCH($J31,Subetapas!$B:$B,0))) | S31: =IF($K31="","",INDEX(Serviços!$A:$A,MATCH($K31,Serviços!$B:$B,0)))

Sheet Resumo Financeiro
A1: Resumo Financeiro
A2: Orçamento Inicial (Previsto) | B2: =Início!$B$8
A3: Aportes | B3: =SUM(TabelaFinanceiro[Aporte])
A4: Alterações Aprovadas | B4: =SUMIFS(TabelaAlteracoes[Impacto no Orçamento],TabelaAlteracoes[Status de Aprovação],"Aprovada")
A5: Orçamento Vigente | B5: =B2+B3+B4
A6: Custo Realizado | B6: =SUM(TabelaFinanceiro[Custo Realizado])
A7: Saldo Orçamentário | B7: =B5-B6
A8: % Orçamento Consumido | B8: =IF(B5=0,"N/D",B6/B5)
A9: Outras Entradas | B9: =SUMIF(TabelaFinanceiro[Tipo],"Outras Entradas",TabelaFinanceiro[Valor])
A10: Outras Saídas | B10: =SUMIF(TabelaFinanceiro[Tipo],"Outras Saídas",TabelaFinanceiro[Valor])
A11: Total de Entradas | B11: =B3+B9
A12: Total Pago | B12: =SUM(TabelaFinanceiro[Total Pago])
A13: Total de Saídas | B13: =B12+B10
A14: Saldo de Caixa | B14: =B11-B13
A15: Total A Pagar | B15: =SUM(TabelaFinanceiro[A Pagar])
A16: Estouro de Orçamento (indicador Operador-only) | B16: =IF(B7<0,"SIM","NÃO")
A18: Nota da Etapa 5: Orçamento Vigente = Orçamento Inicial + Aportes + Alterações Aprovadas (aba Alterações, REG-017 completo).
A19: Nota: 'Estouro de Orçamento' é Operador-only por especificação (Seções 29/30) — o mecanismo técnico de restrição por perfil ainda não existe (SEC_001, [H]).

Sheet Base_Dados
A1: Metadados internos — não editar
A2: ID da Obra (técnico) | B2: OBR-0001
A4: Prefixos de ID técnico homologados (ver Etapa 1, Seção 7)
A5: OBRAS | B5: OBR
A6: ETAPAS | B6: ETA
A7: SUBETAPAS | B7: SUB
A8: SERVICOS_ORCAMENTO | B8: SRV
A9: PLANEJAMENTO | B9: PLN
A10: FORNECEDORES | B10: FOR
A11: COMPRAS | B11: COM
A12: FINANCEIRO | B12: FIN
A13: EXECUCAO_MEDICOES | B13: EXE
A14: ALTERACOES | B14: ALT
A15: PENDENCIAS | B15: PEN
A16: ATUALIZACOES | B16: ATU
... A18: PAGAMENTOS | B18: PGT
A20: Status do Serviço homologados (Etapa 3, Seção 18)
A21: Ativo | B21: integra orçamento corrente
A22: Concluído | B22: integra orçamento corrente
A23: Cancelado | B23: excluído do orçamento corrente
A24: Retirado do Escopo | B24: excluído do orçamento corrente
A25: Substituído | B25: excluído do orçamento corrente
